Workbook

Sheet Resumo
A1: Análise do fornecedor Bem Mulher (Loja de R$10)
A2: Atualizada a cada leva de prints. Produtos com "S" em "Vou comprar?" entram nas contas abaixo, na quantidade da coluna "Quantas caixas/unidades comprar" (aba Produtos).
A4: Indicador | B4: Valor
A5: Produtos analisados | B5: =COUNTA(Produtos!A2:A110) -> 109
A6: Produtos marcados para comprar | B6: =COUNTIF(Produtos!T2:T110,"S") -> 36
A7: Investimento no fornecedor | B7: =SUM(Produtos!Y2:Y110) -> 3869.06
A8: Unidades compradas | B8: =SUMPRODUCT((Produtos!T2:T110="S")*Produtos!F2:F110*Produtos!X2:X110) -> 721
A9: Faturamento se vender tudo no seu site | B9: =SUM(Produtos!V2:V110) -> 10767.9
A10: Lucro se vender tudo no seu site | B10: =SUM(Produtos!W2:W110) -> 5537.1499
A11: Retorno sobre o investimento | B11: =IFERROR(B10/B7,"") -> 1.4311357
A12: Meta de lucro por mês | B12: =Premissas!$B$12 -> 1000
A15: Como usar
A16: • Texto azul com fundo amarelo = você pode alterar (preço de venda, "Vou comprar?", premissas, preço dos kits).
A17: • Preço internet "Estimado" (em dourado) = produto exato não achado; confira no Mercado Livre antes de definir o preço.
A18: • Lucro em vermelho = você perde dinheiro nesse canal com esse preço. No Mercado Livre e na Shopee, prefira vender em kit.
A19: • Use o filtro do cabeçalho na aba Produtos para ordenar por lucro, categoria ou lote.
A20: • Taxas do Mercado Livre e da Shopee são aproximadas: confira as atuais e ajuste na aba Premissas.

Sheet Premissas
A1: Premissas usadas nas contas
A2: Células em amarelo com texto azul podem ser alteradas. O resto da planilha se atualiza sozinho.
A4: Premissa | B4: Valor | C4: Observação
A5: Desconto Pix no seu site | B5: 0.05 | C5: Configuração atual da loja Élan Beauté
A6: Taxa do meio de pagamento (seu site) | B6: 0.01 | C6: Estimativa para Pix; cartão costuma ser 3–5%
A7: Embalagem por pedido/unidade (R$) | B7: 1 | C7: Estimativa: saquinho + etiqueta
A8: Mercado Livre: comissão | B8: 0.12 | C8: Aproximado (anúncio clássico, beleza). Confira a taxa atual
A9: Mercado Livre: taxa fixa por venda abaixo de R$ 79 (R$) | B9: 6.25 | C9: Aproximado. Confira a taxa atual
A10: Shopee: comissão + frete grátis | B10: 0.2 | C10: Aproximado. Confira a taxa atual
A11: Shopee: taxa fixa por item (R$) | B11: 4 | C11: Aproximado. Confira a taxa atual
A12: Meta de lucro por mês (R$) | B12: 1000 | C12: Valor de exemplo: coloque a sua meta

Sheet Produtos
A1: ID | B1: Produto | C1: Marca | D1: Categoria | E1: Lote (print) | F1: Qtd na caixa | G1: Preço no fornecedor | H1: Custo por unidade | I1: Internet: menor preço | J1: Internet: maior preço | K1: Preço internet é | L1: Seu preço de venda | M1: Lucro/un. seu site | N1: Margem seu site | O1: Lucro/un. Mercado Livre | P1: Lucro/un. Shopee | Q1: Lucro da caixa (seu site) | R1: Unidades/mês p/ meta | S1: Recomendação | T1: Vou comprar? (S/N) | U1: Observação | V1: Faturamento (se comprar) | W1: Lucro (se comprar) | X1: Quantas caixas/unidades comprar | Y1: Investimento (se comprar)
A2: P01 | B2: Pó Compacto Choco Fun | C2: Fenzza | D2: Maquiagem – Rosto | E2: 1 | F2: 24 | G2: 156.5 | H2: =IF(ISNUMBER(G2),IFERROR(G2/F2,""),"") -> 6.5208333 | I2: 14.99 | J2: 14.99 | K2: Estimado | L2: 14.9 | M2: =IFERROR(L2*(1-Premissas!$B$5)*(1-Premissas!$B$6)-H2-Premissas!$B$7,"") -> 6.4926167 | N2: =IFERROR(M2/L2,"") -> 0.43574609 | O2: =IFERROR(L2*(1-Premissas!$B$8)-Premissas!$B$9-H2-Premissas!$B$7,"") -> -0.65883333 | P2: =IFERROR(L2*(1-Premissas!$B$10)-Premissas!$B$11-H2-Premissas!$B$7,"") -> 0.39916667 | Q2: =IFERROR(M2*F2,"") -> 155.8228 | R2: =IFERROR(IF(M2>0,ROUNDUP(Premissas!$B$12/M2,0),"sem lucro"),"") -> 155 | S2: Comprar | T2: S | U2: Referência: Pó Solto Choco Fun R$ 14,99 | V2: =IF(AND(T2="S",ISNUMBER(L2),ISNUMBER(F2)),L2*F2*X2,0) -> 357.6 | W2: =IF(AND(T2="S",ISNUMBER(Q2)),Q2*X2,0) -> 155.8228 | X2: 1 | Y2: =IF(AND(T2="S",ISNUMBER(G2)),G2*X2,0) -> 156.5
A3: P02 | B3: Blush Matte Velvet Cheeks | C3: Dapop | D3: Maquiagem – Rosto | E3: 1 | F3: 24 | G3: 161.7 | H3: =IF(ISNUMBER(G3),IFERROR(G3/F3,""),"") -> 6.7375 | I3: 12 | J3: 15.9 | K3: Estimado | L3: 14.9 | M3: =IFERROR(L3*(1-Premissas!$B$5)*(1-Premissas!$B$6)-H3-Premissas!$B$7,"") -> 6.27595 | N3: =IFERROR(M3/L3,"") -> 0.4212047 | O3: =IFERROR(L3*(1-Premissas!$B$8)-Premissas!$B$9-H3-Premissas!$B$7,"") -> -0.8755 | P3: =IFERROR(L3*(1-Premissas!$B$10)-Premissas!$B$11-H3-Premissas!$B$7,"") -> 0.1825 | Q3: =IFERROR(M3*F3,"") -> 150.6228 | R3: =IFERROR(IF(M3>0,ROUNDUP(Premissas!$B$12/M3,0),"sem lucro"),"") -> 160 | S3: Comprar (kit Pele Perfeita) | T3: S | U3: Linha nova; referência: outros blushes Dapop | V3: =IF(AND(T3="S",ISNUMBER(L3),ISNUMBER(F3)),L3*F3*X3,0) -> 357.6 | W3: =IF(AND(T3="S",ISNUMBER(Q3)),Q3*X3,0) -> 150.6228 | X3: 1 | Y3: =IF(AND(T3="S",ISNUMBER(G3)),G3*X3,0) -> 161.7
A4: P03 | B4: Blush Glow Velvet Cheeks | C4: Dapop | D4: Maquiagem – Rosto | E4: 1 | F4: 24 | H4: =IF(ISNUMBER(G4),IFERROR(G4/F4,""),"") | I4: 12 | J4: 15.9 | K4: Estimado | L4: 14.9 | M4: =IFERROR(L4*(1-Premissas!$B$5)*(1-Premissas!$B$6)-H4-Premissas!$B$7,"") | N4: =IFERROR(M4/L4,"") | O4: =IFERROR(L4*(1-Premissas!$B$8)-Premissas!$B$9-H4-Premissas!$B$7,"") | P4: =IFERROR(L4*(1-Premissas!$B$10)-Premissas!$B$11-H4-Premissas!$B$7,"") | Q4: =IFERROR(M4*F4,"") | R4: =IFERROR(IF(M4>0,ROUNDUP(Premissas!$B$12/M4,0),"sem lucro"),"") | S4: Confirmar preço | T4: N | U4: Preço não apareceu no print | V4: =IF(AND(T4="S",ISNUMBER(L4),ISNUMBER(F4)),L4*F4*X4,0) -> 0 | W4: =IF(AND(T4="S",ISNUMBER(Q4)),Q4*X4,0) -> 0 | X4: 1 | Y4: =IF(AND(T4="S",ISNUMBER(G4)),G4*X4,0) -> 0
A5: P04 | B5: Pó Translúcido Solto Soft Focus | C5: Dapop | D5: Maquiagem – Rosto | E5: 1 | F5: 24 | H5: =IF(ISNUMBER(G5),IFERROR(G5/F5,""),"") | K5: Estimado | M5: =IFERROR(L5*(1-Premissas!$B$5)*(1-Premissas!$B$6)-H5-Premissas!$B$7,"") | N5: =IFERROR(M5/L5,"") | O5: =IFERROR(L5*(1-Premissas!$B$8)-Premissas!$B$9-H5-Premissas!$B$7,"") | P5: =IFERROR(L5*(1-Premissas!$B$10)-Premissas!$B$11-H5-Premissas!$B$7,"") | Q5: =IFERROR(M5*F5,"") | R5: =IFERROR(IF(M5>0,ROUNDUP(Premissas!$B$12/M5,0),"sem lucro"),"") | S5: Confirmar preço | T5: N | U5: Preço não apareceu no print | V5: =IF(AND(T5="S",ISNUMBER(L5),ISNUMBER(F5)),L5*F5*X5,0) -> 0 | W5: =IF(AND(T5="S",ISNUMBER(Q5)),Q5*X5,0) -> 0 | X5: 1 | Y5: =IF(AND(T5="S",ISNUMBER(G5)),G5*X5,0) -> 0
A6: P05 | B6: Bronzer Velvet (DP2470) | C6: Dapop | D6: Maquiagem – Rosto | E6: 1 | F6: 24 | G6: 161.7 | H6: =IF(ISNUMBER(G6),IFERROR(G6/F6,""),"") -> 6.7375 | I6: 12 | J6: 15.9 | K6: Estimado | L6: 14.9 | M6: =IFERROR(L6*(1-Premissas!$B$5)*(1-Premissas!$B$6)-H6-Premissas!$B$7,"") -> 6.27595 | N6: =IFERROR(M6/L6,"") -> 0.4212047 | O6: =IFERROR(L6*(1-Premissas!$B$8)-Premissas!$B$9-H6-Premissas!$B$7,"") -> -0.8755 | P6: =IFERROR(L6*(1-Premissas!$B$10)-Premissas!$B$11-H6-Premissas!$B$7,"") -> 0.1825 | Q6: =IFERROR(M6*F6,"") -> 150.6228 | R6: =IFERROR(IF(M6>0,ROUNDUP(Premissas!$B$12/M6,0),"sem lucro"),"") -> 160 | S6: Opcional | T6: N | V6: =IF(AND(T6="S",ISNUMBER(L6),ISNUMBER(F6)),L6*F6*X6,0) -> 0 | W6: =IF(AND(T6="S",ISNUMBER(Q6)),Q6*X6,0) -> 0 | X6: 1 | Y6: =IF(AND(T6="S",ISNUMBER(G6)),G6*X6,0) -> 0
A7: P06 | B7: Contorno Velvet (DP2471) | C7: Dapop | D7: Maquiagem – Rosto | E7: 1 | F7: 24 | G7: 161.7 | H7: =IF(ISNUMBER(G7),IFERROR(G7/F7,""),"") -> 6.7375 | I7: 12 | J7: 15.9 | K7: Estimado | L7: 14.9 | M7: =IFERROR(L7*(1-Premissas!$B$5)*(1-Premissas!$B$6)-H7-Premissas!$B$7,"") -> 6.27595 | N7: =IFERROR(M7/L7,"") -> 0.4212047 | O7: =IFERROR(L7*(1-Premissas!$B$8)-Premissas!$B$9-H7-Premissas!$B$7,"") -> -0.8755 | P7: =IFERROR(L7*(1-Premissas!$B$10)-Premissas!$B$11-H7-Premissas!$B$7,"") -> 0.1825 | Q7: =IFERROR(M7*F7,"") -> 150.6228 | R7: =IFERROR(IF(M7>0,ROUNDUP(Premissas!$B$12/M7,0),"sem lucro"),"") -> 160 | S7: Comprar (kit Pele Perfeita) | T7: S | V7: =IF(AND(T7="S",ISNUMBER(L7),ISNUMBER(F7)),L7*F7*X7,0) -> 357.6 | W7: =IF(AND(T7="S",ISNUMBER(Q7)),Q7*X7,0) -> 150.6228 | X7: 1 | Y7: =IF(AND(T7="S",ISNUMBER(G7)),G7*X7,0) -> 161.7
A8: P07 | B8: Iluminador Velvet Glow | C8: Dapop | D8: Maquiagem – Rosto | E8: 1 | F8: 24 | G8: 163.7 | H8: =IF(ISNUMBER(G8),IFERROR(G8/F8,""),"") -> 6.8208333 | I8: 15.9 | J8: 15.9 | K8: Estimado | L8: 14.9 | M8: =IFERROR(L8*(1-Premissas!$B$5)*(1-Premissas!$B$6)-H8-Premissas!$B$7,"") -> 6.1926167 | N8: =IFERROR(M8/L8,"") -> 0.41561186 | O8: =IFERROR(L8*(1-Premissas!$B$8)-Premissas!$B$9-H8-Premissas!$B$7,"") -> -0.95883333 | P8: =IFERROR(L8*(1-Premissas!$B$10)-Premissas!$B$11-H8-Premissas!$B$7,"") -> 0.099166667 | Q8: =IFERROR(M8*F8,"") -> 148.6228 | R8: =IFERROR(IF(M8>0,ROUNDUP(Premissas!$B$12/M8,0),"sem lucro"),"") -> 162 | S8: Comprar (kit Pele Perfeita) | T8: S | V8: =IF(AND(T8="S",ISNUMBER(L8),ISNUMBER(F8)),L8*F8*X8,0) -> 357.6 | W8: =IF(AND(T8="S",ISNUMBER(Q8)),Q8*X8,0) -> 148.6228 | X8: 1 | Y8: =IF(AND(T8="S",ISNUMBER(G8)),G8*X8,0) -> 163.7
A9: P08 | B9: Pó Facial Matificante Skin Filter | C9: Dapop | D9: Maquiagem – Rosto | E9: 1 | F9: 1 | G9: 5.7 | H9: =IF(ISNUMBER(G9),IFERROR(G9/F9,""),"") -> 5.7 | I9: 7.9 | J9: 10 | K9: Estimado | L9: 11.9 | M9: =IFERROR(L9*(1-Premissas!$B$5)*(1-Premissas!$B$6)-H9-Premissas!$B$7,"") -> 4.49195 | N9: =IFERROR(M9/L9,"") -> 0.37747479 | O9: =IFERROR(L9*(1-Premissas!$B$8)-Premissas!$B$9-H9-Premissas!$B$7,"") -> -2.478 | P9: =IFERROR(L9*(1-Premissas!$B$10)-Premissas!$B$11-H9-Premissas!$B$7,"") -> -1.18 | Q9: =IFERROR(M9*F9,"") -> 4.49195 | R9: =IFERROR(IF(M9>0,ROUNDUP(Premissas!$B$12/M9,0),"sem lucro"),"") -> 223 | S9: Confirmar preço | T9: N | U9: Site diz "C/24 Unid" por R$ 5,70: confirmar se é caixa ou unidade | V9: =IF(AND(T9="S",ISNUMBER(L9),ISNUMBER(F9)),L9*F9*X9,0) -> 0 | W9: =IF(AND(T9="S",ISNUMBER(Q9)),Q9*X9,0) -> 0 | X9: 12 | Y9: =IF(AND(T9="S",ISNUMBER(G9)),G9*X9,0) -> 0
A10: P09 | B10: Água Micelar Pantenol e Ác. Hialurônico 200ml | C10: Dapop | D10: Skincare | E10: 1 | F10: 1 | G10: 5.7 | H10: =IF(ISNUMBER(G10),IFERROR(G10/F10,""),"") -> 5.7 | I10: 9.99 | J10: 12 | K10: Confirmado | L10: 12.9 | M10: =IFERROR(L10*(1-Premissas!$B$5)*(1-Premissas!$B$6)-H10-Premissas!$B$7,"") -> 5.43245 | N10: =IFERROR(M10/L10,"") -> 0.42112016 | O10: =IFERROR(L10*(1-Premissas!$B$8)-Premissas!$B$9-H10-Premissas!$B$7,"") -> -1.598 | P10: =IFERROR(L10*(1-Premissas!$B$10)-Premissas!$B$11-H10-Premissas!$B$7,"") -> -0.38 | Q10: =IFERROR(M10*F10,"") -> 5.43245 | R10: =IFERROR(IF(M10>0,ROUNDUP(Premissas!$B$12/M10,0),"sem lucro"),"") -> 185 | S10: Comprar | T10: S | V10: =IF(AND(T10="S",ISNUMBER(L10),ISNUMBER(F10)),L10*F10*X10,0) -> 154.8 | W10: =IF(AND(T10="S",ISNUMBER(Q10)),Q10*X10,0) -> 65.1894 | X10: 12 | Y10: =IF(AND(T10="S",ISNUMBER(G10)),G10*X10,0) -> 68.4
A11: P10 | B11: Tônico Facial Ácido Glicólico 200ml | C11: Dapop | D11: Skincare | E11: 1 | F11: 1 | G11: 5.7 | H11: =IF(ISNUMBER(G11),IFERROR(G11/F11,""),"") -> 5.7 | I11: 12.9 | J11: 16.99 | K11: Confirmado | L11: 14.9 | M11: =IFERROR(L11*(1-Premissas!$B$5)*(1-Premissas!$B$6)-H11-Premissas!$B$7,"") -> 7.31345 | N11: =IFERROR(M11/L11,"") -> 0.49083557 | O11: =IFERROR(L11*(1-Premissas!$B$8)-Premissas!$B$9-H11-Premissas!$B$7,"") -> 0.162 | P11: =IFERROR(L11*(1-Premissas!$B$10)-Premissas!$B$11-H11-Premissas!$B$7,"") -> 1.22 | Q11: =IFERROR(M11*F11,"") -> 7.31345 | R11: =IFERROR(IF(M11>0,ROUNDUP(Premissas!$B$12/M11,0),"sem lucro"),"") -> 137 | S11: Comprar | T11: S | V11: =IF(AND(T11="S",ISNUMBER(L11),ISNUMBER(F11)),L11*F11*X11,0) -> 178.8 | W11: =IF(AND(T11="S",ISNUMBER(Q11)),Q11*X11,0) -> 87.7614 | X11: 12 | Y11: =IF(AND(T11="S",ISNUMBER(G11)),G11*X11,0) -> 68.4
A12: P11 | B12: Demaquilante Aloe Vera e Alantoína 200ml | C12: Dapop | D12: Skincare | E12: 1 | F12: 1 | G12: 5.7 | H12: =IF(ISNUMBER(G12),IFERROR(G12/F12,""),"") -> 5.7 | I12: 9.99 | J12: 12 | K12: Estimado | L12: 12.9 | M12: =IFERROR(L12*(1-Premissas!$B$5)*(1-Premissas!$B$6)-H12-Premissas!$B$7,"") -> 5.43245 | N12: =IFERROR(M12/L12,"") -> 0.42112016 | O12: =IFERROR(L12*(1-Premissas!$B$8)-Premissas!$B$9-H12-Premissas!$B$7,"") -> -1.598 | P12: =IFERROR(L12*(1-Premissas!$B$10)-Premissas!$B$11-H12-Premissas!$B$7,"") -> -0.38 | Q12: =IFERROR(M12*F12,"") -> 5.43245 | R12: =IFERROR(IF(M12>0,ROUNDUP(Premissas!$B$12/M12,0),"sem lucro"),"") -> 185 | S12: Opcional | T12: N | V12: =IF(AND(T12="S",ISNUMBER(L12),ISNUMBER(F12)),L12*F12*X12,0) -> 0 | W12: =IF(AND(T12="S",ISNUMBER(Q12)),Q12*X12,0) -> 0 | X12: 12 | Y12: =IF(AND(T12="S",ISNUMBER(G12)),G12*X12,0) -> 0
A13: P12 | B13: Loção Adstringente Chá Verde 200ml | C13: Dapop | D13: Skincare | E13: 1 | F13: 1 | G13: 5.7 | H13: =IF(ISNUMBER(G13),IFERROR(G13/F13,""),"") -> 5.7 | I13: 9.99 | J13: 12 | K13: Estimado | L13: 12.9 | M13: =IFERROR(L13*(1-Premissas!$B$5)*(1-Premissas!$B$6)-H13-Premissas!$B$7,"") -> 5.43245 | N13: =IFERROR(M13/L13,"") -> 0.42112016 | O13: =IFERROR(L13*(1-Premissas!$B$8)-Premissas!$B$9-H13-Premissas!$B$7,"") -> -1.598 | P13: =IFERROR(L13*(1-Premissas!$B$10)-Premissas!$B$11-H13-Premissas!$B$7,"") -> -0.38 | Q13: =IFERROR(M13*F13,"") -> 5.43245 | R13: =IFERROR(IF(M13>0,ROUNDUP(Premissas!$B$12/M13,0),"sem lucro"),"") -> 185 | S13: Comprar (kit Rotina Skincare) | T13: S | V13: =IF(AND(T13="S",ISNUMBER(L13),ISNUMBER(F13)),L13*F13*X13,0) -> 154.8 | W13: =IF(AND(T13="S",ISNUMBER(Q13)),Q13*X13,0) -> 65.1894 | X13: 12 | Y13: =IF(AND(T13="S",ISNUMBER(G13)),G13*X13,0) -> 68.4
A14: P13 | B14: Água Micelar Vitamina C e Ác. Hialurônico 200ml | C14: Dapop | D14: Skincare | E14: 1 | F14: 1 | G14: 5.7 | H14: =IF(ISNUMBER(G14),IFERROR(G14/F14,""),"") -> 5.7 | I14: 9.99 | J14: 12 | K14: Confirmado | L14: 12.9 | M14: =IFERROR(L14*(1-Premissas!$B$5)*(1-Premissas!$B$6)-H14-Premissas!$B$7,"") -> 5.43245 | N14: =IFERROR(M14/L14,"") -> 0.42112016 | O14: =IFERROR(L14*(1-Premissas!$B$8)-Premissas!$B$9-H14-Premissas!$B$7,"") -> -1.598 | P14: =IFERROR(L14*(1-Premissas!$B$10)-Premissas!$B$11-H14-Premissas!$B$7,"") -> -0.38 | Q14: =IFERROR(M14*F14,"") -> 5.43245 | R14: =IFERROR(IF(M14>0,ROUNDUP(Premissas!$B$12/M14,0),"sem lucro"),"") -> 185 | S14: Opcional | T14: N | V14: =IF(AND(T14="S",ISNUMBER(L14),ISNUMBER(F14)),L14*F14*X14,0) -> 0 | W14: =IF(AND(T14="S",ISNUMBER(Q14)),Q14*X14,0) -> 0 | X14: 12 | Y14: =IF(AND(T14="S",ISNUMBER(G14)),G14*X14,0) -> 0
A15: P14 | B15: Água Micelar Rosa Mosqueta e Niacinamida 200ml | C15: Dapop | D15: Skincare | E15: 1 | F15: 1 | G15: 5.7 | H15: =IF(ISNUMBER(G15),IFERROR(G15/F15,""),"") -> 5.7 | I15: 9.99 | J15: 12 | K15: Confirmado | L15: 12.9 | M15: =IFERROR(L15*(1-Premissas!$B$5)*(1-Premissas!$B$6)-H15-Premissas!$B$7,"") -> 5.43245 | N15: =IFERROR(M15/L15,"") -> 0.42112016 | O15: =IFERROR(L15*(1-Premissas!$B$8)-Premissas!$B$9-H15-Premissas!$B$7,"") -> -1.598 | P15: =IFERROR(L15*(1-Premissas!$B$10)-Premissas!$B$11-H15-Premissas!$B$7,"") -> -0.38 | Q15: =IFERROR(M15*F15,"") -> 5.43245 | R15: =IFERROR(IF(M15>0,ROUNDUP(Premissas!$B$12/M15,0),"sem lucro"),"") -> 185 | S15: Opcional | T15: N | V15: =IF(AND(T15="S",ISNUMBER(L15),ISNUMBER(F15)),L15*F15*X15,0) -> 0 | W15: =IF(AND(T15="S",ISNUMBER(Q15)),Q15*X15,0) -> 0 | X15: 12 | Y15: =IF(AND(T15="S",ISNUMBER(G15)),G15*X15,0) -> 0
A16: P15 | B16: Kit Esponjas Makeup Blender Puff c/4 | C16: Mahav | D16: Acessórios | E16: 1 | F16: 1 | G16: 5.3 | H16: =IF(ISNUMBER(G16),IFERROR(G16/F16,""),"") -> 5.3 | I16: 13.9 | J16: 19.9 | K16: Confirmado | L16: 16.9 | M16: =IFERROR(L16*(1-Premissas!$B$5)*(1-Premissas!$B$6)-H16-Premissas!$B$7,"") -> 9.59445 | N16: =IFERROR(M16/L16,"") -> 0.56771893 | O16: =IFERROR(L16*(1-Premissas!$B$8)-Premissas!$B$9-H16-Premissas!$B$7,"") -> 2.322 | P16: =IFERROR(L16*(1-Premissas!$B$10)-Premissas!$B$11-H16-Premissas!$B$7,"") -> 3.22 | Q16: =IFERROR(M16*F16,"") -> 9.59445 | R16: =IFERROR(IF(M16>0,ROUNDUP(Premissas!$B$12/M16,0),"sem lucro"),"") -> 105 | S16: Comprar | T16: S | V16: =IF(AND(T16="S",ISNUMBER(L16),ISNUMBER(F16)),L16*F16*X16,0) -> 202.8 | W16: =IF(AND(T16="S",ISNUMBER(Q16)),Q16*X16,0) -> 115.1334 | X16: 12 | Y16: =IF(AND(T16="S",ISNUMBER(G16)),G16*X16,0) -> 63.6
A17: P16 | B17: Esponja Gota Makeup Blender Choco/Cherry | C17: Mahav | D17: Acessórios | E17: 1 | F17: 1 | G17: 2.6 | H17: =IF(ISNUMBER(G17),IFERROR(G17/F17,""),"") -> 2.6 | I17: 6.9 | J17: 6.9 | K17: Estimado | L17: 7.9 | M17: =IFERROR(L17*(1-Premissas!$B$5)*(1-Premissas!$B$6)-H17-Premissas!$B$7,"") -> 3.82995 | N17: =IFERROR(M17/L17,"") -> 0.4848038 | O17: =IFERROR(L17*(1-Premissas!$B$8)-Premissas!$B$9-H17-Premissas!$B$7,"") -> -2.898 | P17: =IFERROR(L17*(1-Premissas!$B$10)-Premissas!$B$11-H17-Premissas!$B$7,"") -> -1.28 | Q17: =IFERROR(M17*F17,"") -> 3.82995 | R17: =IFERROR(IF(M17>0,ROUNDUP(Premissas!$B$12/M17,0),"sem lucro"),"") -> 262 | S17: Só em kit | T17: N | V17: =IF(AND(T17="S",ISNUMBER(L17),ISNUMBER(F17)),L17*F17*X17,0) -> 0 | W17: =IF(AND(T17="S",ISNUMBER(Q17)),Q17*X17,0) -> 0 | X17: 12 | Y17: =IF(AND(T17="S",ISNUMBER(G17)),G17*X17,0) -> 0
A18: P17 | B18: Esponja Chanfrada Makeup Blender Cut | C18: Mahav | D18: Acessórios | E18: 1 | F18: 1 | G18: 2.6 | H18: =IF(ISNUMBER(G18),IFERROR(G18/F18,""),"") -> 2.6 | I18: 6.9 | J18: 6.9 | K18: Estimado | L18: 7.9 | M18: =IFERROR(L18*(1-Premissas!$B$5)*(1-Premissas!$B$6)-H18-Premissas!$B$7,"") -> 3.82995 | N18: =IFERROR(M18/L18,"") -> 0.4848038 | O18: =IFERROR(L18*(1-Premissas!$B$8)-Premissas!$B$9-H18-Premissas!$B$7,"") -> -2.898 | P18: =IFERROR(L18*(1-Premissas!$B$10)-Premissas!$B$11-H18-Premissas!$B$7,"") -> -1.28 | Q18: =IFERROR(M18*F18,"") -> 3.82995 | R18: =IFERROR(IF(M18>0,ROUNDUP(Premissas!$B$12/M18,0),"sem lucro"),"") -> 262 | S18: Só em kit | T18: N | V18: =IF(AND(T18="S",ISNUMBER(L18),ISNUMBER(F18)),L18*F18*X18,0) -> 0 | W18: =IF(AND(T18="S",ISNUMBER(Q18)),Q18*X18,0) -> 0 | X18: 12 | Y18: =IF(AND(T18="S",ISNUMBER(G18)),G18*X18,0) -> 0
A19: P18 | B19: Lips e Cheeks Cream | C19: Miss Romantic | D19: Maquiagem – Lábios | E19: 1 | F19: 24 | G19: 101.99 | H19: =IF(ISNUMBER(G19),IFERROR(G19/F19,""),"") -> 4.2495833 | I19: 10 | J19: 10 | K19: Estimado | L19: 11.9 | M19: =IFERROR(L19*(1-Premissas!$B$5)*(1-Premissas!$B$6)-H19-Premissas!$B$7,"") -> 5.9423667 | N19: =IFERROR(M19/L19,"") -> 0.49935854 | O19: =IFERROR(L19*(1-Premissas!$B$8)-Premissas!$B$9-H19-Premissas!$B$7,"") -> -1.0275833 | P19: =IFERROR(L19*(1-Premissas!$B$10)-Premissas!$B$11-H19-Premissas!$B$7,"") -> 0.27041667 | Q19: =IFERROR(M19*F19,"") -> 142.6168 | R19: =IFERROR(IF(M19>0,ROUNDUP(Premissas!$B$12/M19,0),"sem lucro"),"") -> 169 | S19: Opcional | T19: N | V19: =IF(AND(T19="S",ISNUMBER(L19),ISNUMBER(F19)),L19*F19*X19,0) -> 0 | W19: =IF(AND(T19="S",ISNUMBER(Q19)),Q19*X19,0) -> 0 | X19: 1 | Y19: =IF(AND(T19="S",ISNUMBER(G19)),G19*X19,0) -> 0
A20: P19 | B20: Lip Gloss Sweet | C20: Miss Romantic | D20: Maquiagem – Lábios | E20: 1 | F20: 24 | G20: 90.99 | H20: =IF(ISNUMBER(G20),IFERROR(G20/F20,""),"") -> 3.79125 | I20: 10 | J20: 10 | K20: Estimado | L20: 9.9 | M20: =IFERROR(L20*(1-Premissas!$B$5)*(1-Premissas!$B$6)-H20-Premissas!$B$7,"") -> 4.5197 | N20: =IFERROR(M20/L20,"") -> 0.45653535 | O20: =IFERROR(L20*(1-Premissas!$B$8)-Premissas!$B$9-H20-Premissas!$B$7,"") -> -2.32925 | P20: =IFERROR(L20*(1-Premissas!$B$10)-Premissas!$B$11-H20-Premissas!$B$7,"") -> -0.87125 | Q20: =IFERROR(M20*F20,"") -> 108.4728 | R20: =IFERROR(IF(M20>0,ROUNDUP(Premissas!$B$12/M20,0),"sem lucro"),"") -> 222 | S20: Limitar (muitos gloss) | T20: N | V20: =IF(AND(T20="S",ISNUMBER(L20),ISNUMBER(F20)),L20*F20*X20,0) -> 0 | W20: =IF(AND(T20="S",ISNUMBER(Q20)),Q20*X20,0) -> 0 | X20: 1 | Y20: =IF(AND(T20="S",ISNUMBER(G20)),G20*X20,0) -> 0
A21: P20 | B21: Lip Liner Sweet Linha dos Lábios | C21: Miss Romantic | D21: Maquiagem – Lábios | E21: 1 | F21: 24 | G21: 64.2 | H21: =IF(ISNUMBER(G21),IFERROR(G21/F21,""),"") -> 2.675 | I21: 5 | J21: 10 | K21: Estimado | L21: 7.9 | M21: =IFERROR(L21*(1-Premissas!$B$5)*(1-Premissas!$B$6)-H21-Premissas!$B$7,"") -> 3.75495 | N21: =IFERROR(M21/L21,"") -> 0.47531013 | O21: =IFERROR(L21*(1-Premissas!$B$8)-Premissas!$B$9-H21-Premissas!$B$7,"") -> -2.973 | P21: =IFERROR(L21*(1-Premissas!$B$10)-Premissas!$B$11-H21-Premissas!$B$7,"") -> -1.355 | Q21: =IFERROR(M21*F21,"") -> 90.1188 | R21: =IFERROR(IF(M21>0,ROUNDUP(Premissas!$B$12/M21,0),"sem lucro"),"") -> 267 | S21: Só em kit | T21: N | V21: =IF(AND(T21="S",ISNUMBER(L21),ISNUMBER(F21)),L21*F21*X21,0) -> 0 | W21: =IF(AND(T21="S",ISNUMBER(Q21)),Q21*X21,0) -> 0 | X21: 1 | Y21: =IF(AND(T21="S",ISNUMBER(G21)),G21*X21,0) -> 0
A22: P21 | B22: Máscara para Cílios Natural Curling | C22: Miss Romantic | D22: Maquiagem – Olhos | E22: 2 | F22: 24 | G22: 160.4 | H22: =IF(ISNUMBER(G22),IFERROR(G22/F22,""),"") -> 6.6833333 | I22: 12.9 | J22: 12.9 | K22: Estimado | L22: 12.9 | M22: =IFERROR(L22*(1-Premissas!$B$5)*(1-Premissas!$B$6)-H22-Premissas!$B$7,"") -> 4.4491167 | N22: =IFERROR(M22/L22,"") -> 0.34489276 | O22: =IFERROR(L22*(1-Premissas!$B$8)-Premissas!$B$9-H22-Premissas!$B$7,"") -> -2.5813333 | P22: =IFERROR(L22*(1-Premissas!$B$10)-Premissas!$B$11-H22-Premissas!$B$7,"") -> -1.3633333 | Q22: =IFERROR(M22*F22,"") -> 106.7788 | R22: =IFERROR(IF(M22>0,ROUNDUP(Premissas!$B$12/M22,0),"sem lucro"),"") -> 225 | S22: Trocada pela Super Poderes 36h | T22: N | V22: =IF(AND(T22="S",ISNUMBER(L22),ISNUMBER(F22)),L22*F22*X22,0) -> 0 | W22: =IF(AND(T22="S",ISNUMBER(Q22)),Q22*X22,0) -> 0 | X22: 1 | Y22: =IF(AND(T22="S",ISNUMBER(G22)),G22*X22,0) -> 0
A23: P22 | B23: Cílios Postiços 8D (F007/F011/F012/F019/F022) | C23: Sabrina Sato | D23: Maquiagem – Olhos | E23: 2 | F23: 10 | G23: 37.8 | H23: =IF(ISNUMBER(G23),IFERROR(G23/F23,""),"") -> 3.78 | I23: 4.06 | J23: 10.99 | K23: Confirmado | L23: 9.9 | M23: =IFERROR(L23*(1-Premissas!$B$5)*(1-Premissas!$B$6)-H23-Premissas!$B$7,"") -> 4.53095 | N23: =IFERROR(M23/L23,"") -> 0.45767172 | O23: =IFERROR(L23*(1-Premissas!$B$8)-Premissas!$B$9-H23-Premissas!$B$7,"") -> -2.318 | P23: =IFERROR(L23*(1-Premissas!$B$10)-Premissas!$B$11-H23-Premissas!$B$7,"") -> -0.86 | Q23: =IFERROR(M23*F23,"") -> 45.3095 | R23: =IFERROR(IF(M23>0,ROUNDUP(Premissas!$B$12/M23,0),"sem lucro"),"") -> 221 | S23: Comprar | T23: S | U23: 5 modelos, mesmo preço. Pedir nota fiscal e confirmar que são originais | V23: =IF(AND(T23="S",ISNUMBER(L23),ISNUMBER(F23)),L23*F23*X23,0) -> 99 | W23: =IF(AND(T23="S",ISNUMBER(Q23)),Q23*X23,0) -> 45.3095 | X23: 1 | Y23: =IF(AND(T23="S",ISNUMBER(G23)),G23*X23,0) -> 37.8
A24: P23 | B24: Sérum Facial Ácido Hialurônico Reflection 30ml | C24: Safira | D24: Skincare | E24: 2 | F24: 1 | G24: 6.3 | H24: =IF(ISNUMBER(G24),IFERROR(G24/F24,""),"") -> 6.3 | I24: 15 | J24: 20 | K24: Estimado | L24: 16.9 | M24: =IFERROR(L24*(1-Premissas!$B$5)*(1-Premissas!$B$6)-H24-Premissas!$B$7,"") -> 8.59445 | N24: =IFERROR(M24/L24,"") -> 0.50854734 | O24: =IFERROR(L24*(1-Premissas!$B$8)-Premissas!$B$9-H24-Premissas!$B$7,"") -> 1.322 | P24: =IFERROR(L24*(1-Premissas!$B$10)-Premissas!$B$11-H24-Premissas!$B$7,"") -> 2.22 | Q24: =IFERROR(M24*F24,"") -> 8.59445 | R24: =IFERROR(IF(M24>0,ROUNDUP(Premissas!$B$12/M24,0),"sem lucro"),"") -> 117 | S24: Comprar (kit Pele de Vidro) | T24: S | V24: =IF(AND(T24="S",ISNUMBER(L24),ISNUMBER(F24)),L24*F24*X24,0) -> 202.8 | W24: =IF(AND(T24="S",ISNUMBER(Q24)),Q24*X24,0) -> 103.1334 | X24: 12 | Y24: =IF(AND(T24="S",ISNUMBER(G24)),G24*X24,0) -> 75.6
A25: P24 | B25: Sérum Facial Clareador Reflection 30ml | C25: Safira | D25: Skincare | E25: 2 | F25: 1 | G25: 6.3 | H25: =IF(ISNUMBER(G25),IFERROR(G25/F25,""),"") -> 6.3 | I25: 15 | J25: 20 | K25: Estimado | L25: 16.9 | M25: =IFERROR(L25*(1-Premissas!$B$5)*(1-Premissas!$B$6)-H25-Premissas!$B$7,"") -> 8.59445 | N25: =IFERROR(M25/L25,"") -> 0.50854734 | O25: =IFERROR(L25*(1-Premissas!$B$8)-Premissas!$B$9-H25-Premissas!$B$7,"") -> 1.322 | P25: =IFERROR(L25*(1-Premissas!$B$10)-Premissas!$B$11-H25-Premissas!$B$7,"") -> 2.22 | Q25: =IFERROR(M25*F25,"") -> 8.59445 | R25: =IFERROR(IF(M25>0,ROUNDUP(Premissas!$B$12/M25,0),"sem lucro"),"") -> 117 | S25: Comprar (kit Pele de Vidro) | T25: S | V25: =IF(AND(T25="S",ISNUMBER(L25),ISNUMBER(F25)),L25*F25*X25,0) -> 202.8 | W25: =IF(AND(T25="S",ISNUMBER(Q25)),Q25*X25,0) -> 103.1334 | X25: 12 | Y25: =IF(AND(T25="S",ISNUMBER(G25)),G25*X25,0) -> 75.6
A26: P25 | B26: Sérum Facial Vitamina C Reflection 30ml | C26: Safira | D26: Skincare | E26: 2 | F26: 1 | G26: 6.3 | H26: =IF(ISNUMBER(G26),IFERROR(G26/F26,""),"") -> 6.3 | I26: 15 | J26: 20 | K26: Estimado | L26: 16.9 | M26: =IFERROR(L26*(1-Premissas!$B$5)*(1-Premissas!$B$6)-H26-Premissas!$B$7,"") -> 8.59445 | N26: =IFERROR(M26/L26,"") -> 0.50854734 | O26: =IFERROR(L26*(1-Premissas!$B$8)-Premissas!$B$9-H26-Premissas!$B$7,"") -> 1.322 | P26: =IFERROR(L26*(1-Premissas!$B$10)-Premissas!$B$11-H26-Premissas!$B$7,"") -> 2.22 | Q26: =IFERROR(M26*F26,"") -> 8.59445 | R26: =IFERROR(IF(M26>0,ROUNDUP(Premissas!$B$12/M26,0),"sem lucro"),"") -> 117 | S26: Comprar (kit Pele de Vidro) | T26: S | V26: =IF(AND(T26="S",ISNUMBER(L26),ISNUMBER(F26)),L26*F26*X26,0) -> 202.8 | W26: =IF(AND(T26="S",ISNUMBER(Q26)),Q26*X26,0) -> 103.1334 | X26: 12 | Y26: =IF(AND(T26="S",ISNUMBER(G26)),G26*X26,0) -> 75.6
A27: P26 | B27: Creme Hidratante Ureia 3% 200g | C27: Safira | D27: Corpo | E27: 2 | F27: 1 | G27: 6.9 | H27: =IF(ISNUMBER(G27),IFERROR(G27/F27,""),"") -> 6.9 | I27: 20 | J27: 30 | K27: Estimado | L27: 19.9 | M27: =IFERROR(L27*(1-Premissas!$B$5)*(1-Premissas!$B$6)-H27-Premissas!$B$7,"") -> 10.81595 | N27: =IFERROR(M27/L27,"") -> 0.54351508 | O27: =IFERROR(L27*(1-Premissas!$B$8)-Premissas!$B$9-H27-Premissas!$B$7,"") -> 3.362 | P27: =IFERROR(L27*(1-Premissas!$B$10)-Premissas!$B$11-H27-Premissas!$B$7,"") -> 4.02 | Q27: =IFERROR(M27*F27,"") -> 10.81595 | R27: =IFERROR(IF(M27>0,ROUNDUP(Premissas!$B$12/M27,0),"sem lucro"),"") -> 93 | S27: Comprar | T27: S | U27: Pesado: frete mais caro. Melhor no seu site | V27: =IF(AND(T27="S",ISNUMBER(L27),ISNUMBER(F27)),L27*F27*X27,0) -> 238.8 | W27: =IF(AND(T27="S",ISNUMBER(Q27)),Q27*X27,0) -> 129.7914 | X27: 12 | Y27: =IF(AND(T27="S",ISNUMBER(G27)),G27*X27,0) -> 82.8
A28: P27 | B28: Batom Brilho Natural | C28: Melana | D28: Maquiagem – Lábios | E28: 2 | F28: 24 | G28: 165.3 | H28: =IF(ISNUMBER(G28),IFERROR(G28/F28,""),"") -> 6.8875 | I28: 14.9 | J28: 14.9 | K28: Estimado | L28: 14.9 | M28: =IFERROR(L28*(1-Premissas!$B$5)*(1-Premissas!$B$6)-H28-Premissas!$B$7,"") -> 6.12595 | N28: =IFERROR(M28/L28,"") -> 0.41113758 | O28: =IFERROR(L28*(1-Premissas!$B$8)-Premissas!$B$9-H28-Premissas!$B$7,"") -> -1.0255 | P28: =IFERROR(L28*(1-Premissas!$B$10)-Premissas!$B$11-H28-Premissas!$B$7,"") -> 0.0325 | Q28: =IFERROR(M28*F28,"") -> 147.0228 | R28: =IFERROR(IF(M28>0,ROUNDUP(Premissas!$B$12/M28,0),"sem lucro"),"") -> 164 | S28: Opcional | T28: N | V28: =IF(AND(T28="S",ISNUMBER(L28),ISNUMBER(F28)),L28*F28*X28,0) -> 0 | W28: =IF(AND(T28="S",ISNUMBER(Q28)),Q28*X28,0) -> 0 | X28: 1 | Y28: =IF(AND(T28="S",ISNUMBER(G28)),G28*X28,0) -> 0
A29: P28 | B29: Lip Oil Fruit Juice (LG007) | C29: Hudamoji | D29: Maquiagem – Lábios | E29: 2 | F29: 24 | G29: 95.6 | H29: =IF(ISNUMBER(G29),IFERROR(G29/F29,""),"") -> 3.9833333 | I29: 7.39 | J29: 7.39 | K29: Confirmado | L29: 9.9 | M29: =IFERROR(L29*(1-Premissas!$B$5)*(1-Premissas!$B$6)-H29-Premissas!$B$7,"") -> 4.3276167 | N29: =IFERROR(M29/L29,"") -> 0.437133 | O29: =IFERROR(L29*(1-Premissas!$B$8)-Premissas!$B$9-H29-Premissas!$B$7,"") -> -2.5213333 | P29: =IFERROR(L29*(1-Premissas!$B$10)-Premissas!$B$11-H29-Premissas!$B$7,"") -> -1.0633333 | Q29: =IFERROR(M29*F29,"") -> 103.8628 | R29: =IFERROR(IF(M29>0,ROUNDUP(Premissas!$B$12/M29,0),"sem lucro"),"") -> 232 | S29: Opcional | T29: N | V29: =IF(AND(T29="S",ISNUMBER(L29),ISNUMBER(F29)),L29*F29*X29,0) -> 0 | W29: =IF(AND(T29="S",ISNUMBER(Q29)),Q29*X29,0) -> 0 | X29: 1 | Y29: =IF(AND(T29="S",ISNUMBER(G29)),G29*X29,0) -> 0
A30: P29 | B30: Lip Gloss Alta Pigmentação | C30: Hudamoji | D30: Maquiagem – Lábios | E30: 2 | F30: 24 | G30: 147.5 | H30: =IF(ISNUMBER(G30),IFERROR(G30/F30,""),"") -> 6.1458333 | I30: 12.9 | J30: 12.9 | K30: Estimado | L30: 12.9 | M30: =IFERROR(L30*(1-Premissas!$B$5)*(1-Premissas!$B$6)-H30-Premissas!$B$7,"") -> 4.9866167 | N30: =IFERROR(M30/L30,"") -> 0.38655943 | O30: =IFERROR(L30*(1-Premissas!$B$8)-Premissas!$B$9-H30-Premissas!$B$7,"") -> -2.0438333 | P30: =IFERROR(L30*(1-Premissas!$B$10)-Premissas!$B$11-H30-Premissas!$B$7,"") -> -0.82583333 | Q30: =IFERROR(M30*F30,"") -> 119.6788 | R30: =IFERROR(IF(M30>0,ROUNDUP(Premissas!$B$12/M30,0),"sem lucro"),"") -> 201 | S30: Limitar (muitos gloss) | T30: N | V30: =IF(AND(T30="S",ISNUMBER(L30),ISNUMBER(F30)),L30*F30*X30,0) -> 0 | W30: =IF(AND(T30="S",ISNUMBER(Q30)),Q30*X30,0) -> 0 | X30: 1 | Y30: =IF(AND(T30="S",ISNUMBER(G30)),G30*X30,0) -> 0
A31: P30 | B31: Iluminador Compacto | C31: JummyJu | D31: Maquiagem – Rosto | E31: 2 | F31: 24 | G31: 113.3 | H31: =IF(ISNUMBER(G31),IFERROR(G31/F31,""),"") -> 4.7208333 | I31: 12.9 | J31: 12.9 | K31: Estimado | L31: 12.9 | M31: =IFERROR(L31*(1-Premissas!$B$5)*(1-Premissas!$B$6)-H31-Premissas!$B$7,"") -> 6.4116167 | N31: =IFERROR(M31/L31,"") -> 0.49702455 | O31: =IFERROR(L31*(1-Premissas!$B$8)-Premissas!$B$9-H31-Premissas!$B$7,"") -> -0.61883333 | P31: =IFERROR(L31*(1-Premissas!$B$10)-Premissas!$B$11-H31-Premissas!$B$7,"") -> 0.59916667 | Q31: =IFERROR(M31*F31,"") -> 153.8788 | R31: =IFERROR(IF(M31>0,ROUNDUP(Premissas!$B$12/M31,0),"sem lucro"),"") -> 156 | S31: Opcional | T31: N | V31: =IF(AND(T31="S",ISNUMBER(L31),ISNUMBER(F31)),L31*F31*X31,0) -> 0 | W31: =IF(AND(T31="S",ISNUMBER(Q31)),Q31*X31,0) -> 0 | X31: 1 | Y31: =IF(AND(T31="S",ISNUMBER(G31)),G31*X31,0) -> 0
A32: P31 | B32: Máscara para Sobrancelhas Tatoo Brow | C32: Femme Paris | D32: Maquiagem – Sobrancelhas | E32: 2 | F32: 24 | G32: 110.8 | H32: =IF(ISNUMBER(G32),IFERROR(G32/F32,""),"") -> 4.6166667 | I32: 12 | J32: 15 | K32: Estimado | L32: 12.9 | M32: =IFERROR(L32*(1-Premissas!$B$5)*(1-Premissas!$B$6)-H32-Premissas!$B$7,"") -> 6.5157833 | N32: =IFERROR(M32/L32,"") -> 0.50509948 | O32: =IFERROR(L32*(1-Premissas!$B$8)-Premissas!$B$9-H32-Premissas!$B$7,"") -> -0.51466667 | P32: =IFERROR(L32*(1-Premissas!$B$10)-Premissas!$B$11-H32-Premissas!$B$7,"") -> 0.70333333 | Q32: =IFERROR(M32*F32,"") -> 156.3788 | R32: =IFERROR(IF(M32>0,ROUNDUP(Premissas!$B$12/M32,0),"sem lucro"),"") -> 154 | S32: Comprar (kits) | T32: S | V32: =IF(AND(T32="S",ISNUMBER(L32),ISNUMBER(F32)),L32*F32*X32,0) -> 309.6 | W32: =IF(AND(T32="S",ISNUMBER(Q32)),Q32*X32,0) -> 156.3788 | X32: 1 | Y32: =IF(AND(T32="S",ISNUMBER(G32)),G32*X32,0) -> 110.8
A33: P32 | B33: Contorno Stick | C33: Femme Paris | D33: Maquiagem – Rosto | E33: 2 | F33: 24 | G33: 151.7 | H33: =IF(ISNUMBER(G33),IFERROR(G33/F33,""),"") -> 6.3208333 | I33: 15.9 | J33: 15.9 | K33: Estimado | L33: 15.9 | M33: =IFERROR(L33*(1-Premissas!$B$5)*(1-Premissas!$B$6)-H33-Premissas!$B$7,"") -> 7.6331167 | N33: =IFERROR(M33/L33,"") -> 0.48007023 | O33: =IFERROR(L33*(1-Premissas!$B$8)-Premissas!$B$9-H33-Premissas!$B$7,"") -> 0.42116667 | P33: =IFERROR(L33*(1-Premissas!$B$10)-Premissas!$B$11-H33-Premissas!$B$7,"") -> 1.3991667 | Q33: =IFERROR(M33*F33,"") -> 183.1948 | R33: =IFERROR(IF(M33>0,ROUNDUP(Premissas!$B$12/M33,0),"sem lucro"),"") -> 132 | S33: Comprar | T33: S | V33: =IF(AND(T33="S",ISNUMBER(L33),ISNUMBER(F33)),L33*F33*X33,0) -> 381.6 | W33: =IF(AND(T33="S",ISNUMBER(Q33)),Q33*X33,0) -> 183.1948 | X33: 1 | Y33: =IF(AND(T33="S",ISNUMBER(G33)),G33*X33,0) -> 151.7
A34: P33 | B34: Lip Gloss Peel-Off | C34: Femme Paris | D34: Maquiagem – Lábios | E34: 3 | F34: 24 | G34: 131.3 | H34: =IF(ISNUMBER(G34),IFERROR(G34/F34,""),"") -> 5.4708333 | I34: 12.9 | J34: 12.9 | K34: Estimado | L34: 12.9 | M34: =IFERROR(L34*(1-Premissas!$B$5)*(1-Premissas!$B$6)-H34-Premissas!$B$7,"") -> 5.6616167 | N34: =IFERROR(M34/L34,"") -> 0.43888501 | O34: =IFERROR(L34*(1-Premissas!$B$8)-Premissas!$B$9-H34-Premissas!$B$7,"") -> -1.3688333 | P34: =IFERROR(L34*(1-Premissas!$B$10)-Premissas!$B$11-H34-Premissas!$B$7,"") -> -0.15083333 | Q34: =IFERROR(M34*F34,"") -> 135.8788 | R34: =IFERROR(IF(M34>0,ROUNDUP(Premissas!$B$12/M34,0),"sem lucro"),"") -> 177 | S34: Comprar (1 das 2 linhas de gloss) | T34: S | U34: Tendência | V34: =IF(AND(T34="S",ISNUMBER(L34),ISNUMBER(F34)),L34*F34*X34,0) -> 309.6 | W34: =IF(AND(T34="S",ISNUMBER(Q34)),Q34*X34,0) -> 135.8788 | X34: 1 | Y34: =IF(AND(T34="S",ISNUMBER(G34)),G34*X34,0) -> 131.3
A35: P34 | B35: Conjunto de Pentes e Acessórios c/9 peças | C35: — | D35: Cabelos | E35: 3 | F35: 1 | G35: 6.5 | H35: =IF(ISNUMBER(G35),IFERROR(G35/F35,""),"") -> 6.5 | I35: 15 | J35: 20 | K35: Estimado | L35: 16.9 | M35: =IFERROR(L35*(1-Premissas!$B$5)*(1-Premissas!$B$6)-H35-Premissas!$B$7,"") -> 8.39445 | N35: =IFERROR(M35/L35,"") -> 0.49671302 | O35: =IFERROR(L35*(1-Premissas!$B$8)-Premissas!$B$9-H35-Premissas!$B$7,"") -> 1.122 | P35: =IFERROR(L35*(1-Premissas!$B$10)-Premissas!$B$11-H35-Premissas!$B$7,"") -> 2.02 | Q35: =IFERROR(M35*F35,"") -> 8.39445 | R35: =IFERROR(IF(M35>0,ROUNDUP(Premissas!$B$12/M35,0),"sem lucro"),"") -> 120 | S35: Comprar | T35: S | V35: =IF(AND(T35="S",ISNUMBER(L35),ISNUMBER(F35)),L35*F35*X35,0) -> 202.8 | W35: =IF(AND(T35="S",ISNUMBER(Q35)),Q35*X35,0) -> 100.7334 | X35: 12 | Y35: =IF(AND(T35="S",ISNUMBER(G35)),G35*X35,0) -> 78
A36: P35 | B36: Mini Esponja para Maquiagem c/4 | C36: Rub… (confirmar marca) | D36: Acessórios | E36: 3 | F36: 1 | G36: 3.2 | H36: =IF(ISNUMBER(G36),IFERROR(G36/F36,""),"") -> 3.2 | I36: 9.9 | J36: 9.9 | K36: Estimado | L36: 9.9 | M36: =IFERROR(L36*(1-Premissas!$B$5)*(1-Premissas!$B$6)-H36-Premissas!$B$7,"") -> 5.11095 | N36: =IFERROR(M36/L36,"") -> 0.51625758 | O36: =IFERROR(L36*(1-Premissas!$B$8)-Premissas!$B$9-H36-Premissas!$B$7,"") -> -1.738 | P36: =IFERROR(L36*(1-Premissas!$B$10)-Premissas!$B$11-H36-Premissas!$B$7,"") -> -0.28 | Q36: =IFERROR(M36*F36,"") -> 5.11095 | R36: =IFERROR(IF(M36>0,ROUNDUP(Premissas!$B$12/M36,0),"sem lucro"),"") -> 196 | S36: Opcional | T36: N | V36: =IF(AND(T36="S",ISNUMBER(L36),ISNUMBER(F36)),L36*F36*X36,0) -> 0 | W36: =IF(AND(T36="S",ISNUMBER(Q36)),Q36*X36,0) -> 0 | X36: 12 | Y36: =IF(AND(T36="S",ISNUMBER(G36)),G36*X36,0) -> 0
A37: P36 | B37: Pó de Tapioca Lilás Selva Neon | C37: Miss Rôse | D37: Maquiagem – Rosto | E37: 3 | F37: 15 | G37: 49.5 | H37: =IF(ISNUMBER(G37),IFERROR(G37/F37,""),"") -> 3.3 | I37: 7.54 | J37: 11.99 | K37: Confirmado | L37: 11.9 | M37: =IFERROR(L37*(1-Premissas!$B$5)*(1-Premissas!$B$6)-H37-Premissas!$B$7,"") -> 6.89195 | N37: =IFERROR(M37/L37,"") -> 0.57915546 | O37: =IFERROR(L37*(1-Premissas!$B$8)-Premissas!$B$9-H37-Premissas!$B$7,"") -> -0.078 | P37: =IFERROR(L37*(1-Premissas!$B$10)-Premissas!$B$11-H37-Premissas!$B$7,"") -> 1.22 | Q37: =IFERROR(M37*F37,"") -> 103.37925 | R37: =IFERROR(IF(M37>0,ROUNDUP(Premissas!$B$12/M37,0),"sem lucro"),"") -> 146 | S37: Comprar | T37: S | U37: Melhor custo da lista | V37: =IF(AND(T37="S",ISNUMBER(L37),ISNUMBER(F37)),L37*F37*X37,0) -> 178.5 | W37: =IF(AND(T37="S",ISNUMBER(Q37)),Q37*X37,0) -> 103.37925 | X37: 1 | Y37: =IF(AND(T37="S",ISNUMBER(G37)),G37*X37,0) -> 49.5
A38: P37 | B38: Tint Brow Preenche Sobrancelha | C38: Wike Make | D38: Maquiagem – Sobrancelhas | E38: 3 | F38: 24 | G38: 150.6 | H38: =IF(ISNUMBER(G38),IFERROR(G38/F38,""),"") -> 6.275 | I38: 12.9 | J38: 12.9 | K38: Estimado | L38: 12.9 | M38: =IFERROR(L38*(1-Premissas!$B$5)*(1-Premissas!$B$6)-H38-Premissas!$B$7,"") -> 4.85745 | N38: =IFERROR(M38/L38,"") -> 0.37654651 | O38: =IFERROR(L38*(1-Premissas!$B$8)-Premissas!$B$9-H38-Premissas!$B$7,"") -> -2.173 | P38: =IFERROR(L38*(1-Premissas!$B$10)-Premissas!$B$11-H38-Premissas!$B$7,"") -> -0.955 | Q38: =IFERROR(M38*F38,"") -> 116.5788 | R38: =IFERROR(IF(M38>0,ROUNDUP(Premissas!$B$12/M38,0),"sem lucro"),"") -> 206 | S38: Comprar (kit Sobrancelha) | T38: S | V38: =IF(AND(T38="S",ISNUMBER(L38),ISNUMBER(F38)),L38*F38*X38,0) -> 309.6 | W38: =IF(AND(T38="S",ISNUMBER(Q38)),Q38*X38,0) -> 116.5788 | X38: 1 | Y38: =IF(AND(T38="S",ISNUMBER(G38)),G38*X38,0) -> 150.6
A39: P38 | B39: Gel Fixador de Sobrancelhas com Pente | C39: Wike Make | D39: Maquiagem – Sobrancelhas | E39: 3 | F39: 24 | G39: 138.2 | H39: =IF(ISNUMBER(G39),IFERROR(G39/F39,""),"") -> 5.7583333 | I39: 12.9 | J39: 12.9 | K39: Estimado | L39: 12.9 | M39: =IFERROR(L39*(1-Premissas!$B$5)*(1-Premissas!$B$6)-H39-Premissas!$B$7,"") -> 5.3741167 | N39: =IFERROR(M39/L39,"") -> 0.41659819 | O39: =IFERROR(L39*(1-Premissas!$B$8)-Premissas!$B$9-H39-Premissas!$B$7,"") -> -1.6563333 | P39: =IFERROR(L39*(1-Premissas!$B$10)-Premissas!$B$11-H39-Premissas!$B$7,"") -> -0.43833333 | Q39: =IFERROR(M39*F39,"") -> 128.9788 | R39: =IFERROR(IF(M39>0,ROUNDUP(Premissas!$B$12/M39,0),"sem lucro"),"") -> 187 | S39: Comprar (kit Sobrancelha) | T39: S | V39: =IF(AND(T39="S",ISNUMBER(L39),ISNUMBER(F39)),L39*F39*X39,0) -> 309.6 | W39: =IF(AND(T39="S",ISNUMBER(Q39)),Q39*X39,0) -> 128.9788 | X39: 1 | Y39: =IF(AND(T39="S",ISNUMBER(G39)),G39*X39,0) -> 138.2
A40: P39 | B40: Lip Gloss Candy | C40: Wike Make | D40: Maquiagem – Lábios | E40: 3 | F40: 24 | G40: 153.6 | H40: =IF(ISNUMBER(G40),IFERROR(G40/F40,""),"") -> 6.4 | I40: 7.52 | J40: 10 | K40: Confirmado | L40: 11.9 | M40: =IFERROR(L40*(1-Premissas!$B$5)*(1-Premissas!$B$6)-H40-Premissas!$B$7,"") -> 3.79195 | N40: =IFERROR(M40/L40,"") -> 0.31865126 | O40: =IFERROR(L40*(1-Premissas!$B$8)-Premissas!$B$9-H40-Premissas!$B$7,"") -> -3.178 | P40: =IFERROR(L40*(1-Premissas!$B$10)-Premissas!$B$11-H40-Premissas!$B$7,"") -> -1.88 | Q40: =IFERROR(M40*F40,"") -> 91.0068 | R40: =IFERROR(IF(M40>0,ROUNDUP(Premissas!$B$12/M40,0),"sem lucro"),"") -> 264 | S40: Evitar (margem baixa) | T40: N | U40: Vendido por R$ 7,50–10 em outras lojas | V40: =IF(AND(T40="S",ISNUMBER(L40),ISNUMBER(F40)),L40*F40*X40,0) -> 0 | W40: =IF(AND(T40="S",ISNUMBER(Q40)),Q40*X40,0) -> 0 | X40: 1 | Y40: =IF(AND(T40="S",ISNUMBER(G40)),G40*X40,0) -> 0
A41: P40 | B41: Lip Gloss Ice Cream | C41: Wike Make | D41: Maquiagem – Lábios | E41: 3 | F41: 24 | G41: 153.6 | H41: =IF(ISNUMBER(G41),IFERROR(G41/F41,""),"") -> 6.4 | I41: 7.52 | J41: 10 | K41: Confirmado | L41: 11.9 | M41: =IFERROR(L41*(1-Premissas!$B$5)*(1-Premissas!$B$6)-H41-Premissas!$B$7,"") -> 3.79195 | N41: =IFERROR(M41/L41,"") -> 0.31865126 | O41: =IFERROR(L41*(1-Premissas!$B$8)-Premissas!$B$9-H41-Premissas!$B$7,"") -> -3.178 | P41: =IFERROR(L41*(1-Premissas!$B$10)-Premissas!$B$11-H41-Premissas!$B$7,"") -> -1.88 | Q41: =IFERROR(M41*F41,"") -> 91.0068 | R41: =IFERROR(IF(M41>0,ROUNDUP(Premissas!$B$12/M41,0),"sem lucro"),"") -> 264 | S41: Evitar (margem baixa) | T41: N | U41: Vendido por R$ 7,50–10 em outras lojas | V41: =IF(AND(T41="S",ISNUMBER(L41),ISNUMBER(F41)),L41*F41*X41,0) -> 0 | W41: =IF(AND(T41="S",ISNUMBER(Q41)),Q41*X41,0) -> 0 | X41: 1 | Y41: =IF(AND(T41="S",ISNUMBER(G41)),G41*X41,0) -> 0
A42: P41 | B42: Lip Gloss Pompom | C42: Wike Make | D42: Maquiagem – Lábios | E42: 3 | F42: 24 | G42: 144.4 | H42: =IF(ISNUMBER(G42),IFERROR(G42/F42,""),"") -> 6.0166667 | I42: 7.52 | J42: 10 | K42: Confirmado | L42: 11.9 | M42: =IFERROR(L42*(1-Premissas!$B$5)*(1-Premissas!$B$6)-H42-Premissas!$B$7,"") -> 4.1752833 | N42: =IFERROR(M42/L42,"") -> 0.35086415 | O42: =IFERROR(L42*(1-Premissas!$B$8)-Premissas!$B$9-H42-Premissas!$B$7,"") -> -2.7946667 | P42: =IFERROR(L42*(1-Premissas!$B$10)-Premissas!$B$11-H42-Premissas!$B$7,"") -> -1.4966667 | Q42: =IFERROR(M42*F42,"") -> 100.2068 | R42: =IFERROR(IF(M42>0,ROUNDUP(Premissas!$B$12/M42,0),"sem lucro"),"") -> 240 | S42: Evitar (margem baixa) | T42: N | V42: =IF(AND(T42="S",ISNUMBER(L42),ISNUMBER(F42)),L42*F42*X42,0) -> 0 | W42: =IF(AND(T42="S",ISNUMBER(Q42)),Q42*X42,0) -> 0 | X42: 1 | Y42: =IF(AND(T42="S",ISNUMBER(G42)),G42*X42,0) -> 0
A43: P42 | B43: Lip Gloss com Chaveiro | C43: Wike Make | D43: Maquiagem – Lábios | E43: 3 | F43: 24 | G43: 138.2 | H43: =IF(ISNUMBER(G43),IFERROR(G43/F43,""),"") -> 5.7583333 | I43: 7.52 | J43: 10 | K43: Confirmado | L43: 11.9 | M43: =IFERROR(L43*(1-Premissas!$B$5)*(1-Premissas!$B$6)-H43-Premissas!$B$7,"") -> 4.4336167 | N43: =IFERROR(M43/L43,"") -> 0.37257283 | O43: =IFERROR(L43*(1-Premissas!$B$8)-Premissas!$B$9-H43-Premissas!$B$7,"") -> -2.5363333 | P43: =IFERROR(L43*(1-Premissas!$B$10)-Premissas!$B$11-H43-Premissas!$B$7,"") -> -1.2383333 | Q43: =IFERROR(M43*F43,"") -> 106.4068 | R43: =IFERROR(IF(M43>0,ROUNDUP(Premissas!$B$12/M43,0),"sem lucro"),"") -> 226 | S43: Comprar (1 das 2 linhas de gloss) | T43: S | U43: Bom para presente | V43: =IF(AND(T43="S",ISNUMBER(L43),ISNUMBER(F43)),L43*F43*X43,0) -> 285.6 | W43: =IF(AND(T43="S",ISNUMBER(Q43)),Q43*X43,0) -> 106.4068 | X43: 1 | Y43: =IF(AND(T43="S",ISNUMBER(G43)),G43*X43,0) -> 138.2
A44: P43 | B44: Lip Gloss (ME005) | C44: Belle Angel | D44: Maquiagem – Lábios | E44: 3 | F44: 24 | G44: 166.3 | H44: =IF(ISNUMBER(G44),IFERROR(G44/F44,""),"") -> 6.9291667 | I44: 12.9 | J44: 12.9 | K44: Estimado | L44: 12.9 | M44: =IFERROR(L44*(1-Premissas!$B$5)*(1-Premissas!$B$6)-H44-Premissas!$B$7,"") -> 4.2032833 | N44: =IFERROR(M44/L44,"") -> 0.32583592 | O44: =IFERROR(L44*(1-Premissas!$B$8)-Premissas!$B$9-H44-Premissas!$B$7,"") -> -2.8271667 | P44: =IFERROR(L44*(1-Premissas!$B$10)-Premissas!$B$11-H44-Premissas!$B$7,"") -> -1.6091667 | Q44: =IFERROR(M44*F44,"") -> 100.8788 | R44: =IFERROR(IF(M44>0,ROUNDUP(Premissas!$B$12/M44,0),"sem lucro"),"") -> 238 | S44: Limitar (muitos gloss) | T44: N | V44: =IF(AND(T44="S",ISNUMBER(L44),ISNUMBER(F44)),L44*F44*X44,0) -> 0 | W44: =IF(AND(T44="S",ISNUMBER(Q44)),Q44*X44,0) -> 0 | X44: 1 | Y44: =IF(AND(T44="S",ISNUMBER(G44)),G44*X44,0) -> 0
A45: P44 | B45: Hidratante Corporal Body Cream Libertad 150ml | C45: Cap Life | D45: Corpo | E45: 3 | F45: 1 | G45: 5.7 | H45: =IF(ISNUMBER(G45),IFERROR(G45/F45,""),"") -> 5.7 | I45: 14.9 | J45: 14.9 | K45: Estimado | L45: 14.9 | M45: =IFERROR(L45*(1-Premissas!$B$5)*(1-Premissas!$B$6)-H45-Premissas!$B$7,"") -> 7.31345 | N45: =IFERROR(M45/L45,"") -> 0.49083557 | O45: =IFERROR(L45*(1-Premissas!$B$8)-Premissas!$B$9-H45-Premissas!$B$7,"") -> 0.162 | P45: =IFERROR(L45*(1-Premissas!$B$10)-Premissas!$B$11-H45-Premissas!$B$7,"") -> 1.22 | Q45: =IFERROR(M45*F45,"") -> 7.31345 | R45: =IFERROR(IF(M45>0,ROUNDUP(Premissas!$B$12/M45,0),"sem lucro"),"") -> 137 | S45: Comprar | T45: S | V45: =IF(AND(T45="S",ISNUMBER(L45),ISNUMBER(F45)),L45*F45*X45,0) -> 178.8 | W45: =IF(AND(T45="S",ISNUMBER(Q45)),Q45*X45,0) -> 87.7614 | X45: 12 | Y45: =IF(AND(T45="S",ISNUMBER(G45)),G45*X45,0) -> 68.4
A46: P45 | B46: Super Hidratante Corporal e Facial Vitamina C 150g | C46: Better Me | D46: Corpo | E46: 4 | F46: 1 | G46: 6.2 | H46: =IF(ISNUMBER(G46),IFERROR(G46/F46,""),"") -> 6.2 | I46: 14.9 | J46: 19.9 | K46: Estimado | L46: 16.9 | M46: =IFERROR(L46*(1-Premissas!$B$5)*(1-Premissas!$B$6)-H46-Premissas!$B$7,"") -> 8.69445 | N46: =IFERROR(M46/L46,"") -> 0.5144645 | O46: =IFERROR(L46*(1-Premissas!$B$8)-Premissas!$B$9-H46-Premissas!$B$7,"") -> 1.422 | P46: =IFERROR(L46*(1-Premissas!$B$10)-Premissas!$B$11-H46-Premissas!$B$7,"") -> 2.32 | Q46: =IFERROR(M46*F46,"") -> 8.69445 | R46: =IFERROR(IF(M46>0,ROUNDUP(Premissas!$B$12/M46,0),"sem lucro"),"") -> 116 | S46: Comprar | T46: S | U46: Outras versões (pêssego, baunilha) à venda no ML/Shopee | V46: =IF(AND(T46="S",ISNUMBER(L46),ISNUMBER(F46)),L46*F46*X46,0) -> 202.8 | W46: =IF(AND(T46="S",ISNUMBER(Q46)),Q46*X46,0) -> 104.3334 | X46: 12 | Y46: =IF(AND(T46="S",ISNUMBER(G46)),G46*X46,0) -> 74.4
A47: P46 | B47: Super Esfoliante Corporal e Facial Vitamina C 150g | C47: Better Me | D47: Corpo | E47: 4 | F47: 1 | G47: 6.5 | H47: =IF(ISNUMBER(G47),IFERROR(G47/F47,""),"") -> 6.5 | I47: 14.9 | J47: 19.9 | K47: Estimado | L47: 16.9 | M47: =IFERROR(L47*(1-Premissas!$B$5)*(1-Premissas!$B$6)-H47-Premissas!$B$7,"") -> 8.39445 | N47: =IFERROR(M47/L47,"") -> 0.49671302 | O47: =IFERROR(L47*(1-Premissas!$B$8)-Premissas!$B$9-H47-Premissas!$B$7,"") -> 1.122 | P47: =IFERROR(L47*(1-Premissas!$B$10)-Premissas!$B$11-H47-Premissas!$B$7,"") -> 2.02 | Q47: =IFERROR(M47*F47,"") -> 8.39445 | R47: =IFERROR(IF(M47>0,ROUNDUP(Premissas!$B$12/M47,0),"sem lucro"),"") -> 120 | S47: Opcional | T47: N | V47: =IF(AND(T47="S",ISNUMBER(L47),ISNUMBER(F47)),L47*F47*X47,0) -> 0 | W47: =IF(AND(T47="S",ISNUMBER(Q47)),Q47*X47,0) -> 0 | X47: 12 | Y47: =IF(AND(T47="S",ISNUMBER(G47)),G47*X47,0) -> 0
A48: P47 | B48: Batom Líquido Matte Touch | C48: Pink 21 | D48: Maquiagem – Lábios | E48: 4 | F48: 48 | G48: 252.8 | H48: =IF(ISNUMBER(G48),IFERROR(G48/F48,""),"") -> 5.2666667 | I48: 10 | J48: 24.99 | K48: Estimado | L48: 14.9 | M48: =IFERROR(L48*(1-Premissas!$B$5)*(1-Premissas!$B$6)-H48-Premissas!$B$7,"") -> 7.7467833 | N48: =IFERROR(M48/L48,"") -> 0.51991834 | O48: =IFERROR(L48*(1-Premissas!$B$8)-Premissas!$B$9-H48-Premissas!$B$7,"") -> 0.59533333 | P48: =IFERROR(L48*(1-Premissas!$B$10)-Premissas!$B$11-H48-Premissas!$B$7,"") -> 1.6533333 | Q48: =IFERROR(M48*F48,"") -> 371.8456 | R48: =IFERROR(IF(M48>0,ROUNDUP(Premissas!$B$12/M48,0),"sem lucro"),"") -> 130 | S48: Opcional | T48: N | U48: Caixa com 48 | V48: =IF(AND(T48="S",ISNUMBER(L48),ISNUMBER(F48)),L48*F48*X48,0) -> 0 | W48: =IF(AND(T48="S",ISNUMBER(Q48)),Q48*X48,0) -> 0 | X48: 1 | Y48: =IF(AND(T48="S",ISNUMBER(G48)),G48*X48,0) -> 0
A49: P48 | B49: Batom Líquido Beauty | C49: Pink 21 | D49: Maquiagem – Lábios | E49: 4 | F49: 24 | G49: 158.8 | H49: =IF(ISNUMBER(G49),IFERROR(G49/F49,""),"") -> 6.6166667 | I49: 10 | J49: 24.99 | K49: Estimado | L49: 14.9 | M49: =IFERROR(L49*(1-Premissas!$B$5)*(1-Premissas!$B$6)-H49-Premissas!$B$7,"") -> 6.3967833 | N49: =IFERROR(M49/L49,"") -> 0.42931432 | O49: =IFERROR(L49*(1-Premissas!$B$8)-Premissas!$B$9-H49-Premissas!$B$7,"") -> -0.75466667 | P49: =IFERROR(L49*(1-Premissas!$B$10)-Premissas!$B$11-H49-Premissas!$B$7,"") -> 0.30333333 | Q49: =IFERROR(M49*F49,"") -> 153.5228 | R49: =IFERROR(IF(M49>0,ROUNDUP(Premissas!$B$12/M49,0),"sem lucro"),"") -> 157 | S49: Opcional | T49: N | V49: =IF(AND(T49="S",ISNUMBER(L49),ISNUMBER(F49)),L49*F49*X49,0) -> 0 | W49: =IF(AND(T49="S",ISNUMBER(Q49)),Q49*X49,0) -> 0 | X49: 1 | Y49: =IF(AND(T49="S",ISNUMBER(G49)),G49*X49,0) -> 0
A50: P49 | B50: Batom Líquido Efeito Matte All Day | C50: Pink 21 | D50: Maquiagem – Lábios | E50: 4 | F50: 48 | G50: 271.6 | H50: =IF(ISNUMBER(G50),IFERROR(G50/F50,""),"") -> 5.6583333 | I50: 10 | J50: 24.99 | K50: Confirmado | L50: 14.9 | M50: =IFERROR(L50*(1-Premissas!$B$5)*(1-Premissas!$B$6)-H50-Premissas!$B$7,"") -> 7.3551167 | N50: =IFERROR(M50/L50,"") -> 0.49363199 | O50: =IFERROR(L50*(1-Premissas!$B$8)-Premissas!$B$9-H50-Premissas!$B$7,"") -> 0.20366667 | P50: =IFERROR(L50*(1-Premissas!$B$10)-Premissas!$B$11-H50-Premissas!$B$7,"") -> 1.2616667 | Q50: =IFERROR(M50*F50,"") -> 353.0456 | R50: =IFERROR(IF(M50>0,ROUNDUP(Premissas!$B$12/M50,0),"sem lucro"),"") -> 136 | S50: Comprar (1 linha de batom) | T50: S | U50: Caixa com 48. Visto de R$ 10 a R$ 24,99 | V50: =IF(AND(T50="S",ISNUMBER(L50),ISNUMBER(F50)),L50*F50*X50,0) -> 715.2 | W50: =IF(AND(T50="S",ISNUMBER(Q50)),Q50*X50,0) -> 353.0456 | X50: 1 | Y50: =IF(AND(T50="S",ISNUMBER(G50)),G50*X50,0) -> 271.6
A51: P50 | B51: Pó Solto Banana Soft Sheer | C51: Alleva | D51: Maquiagem – Rosto | E51: 4 | F51: 18 | G51: 89.6 | H51: =IF(ISNUMBER(G51),IFERROR(G51/F51,""),"") -> 4.9777778 | I51: 12.9 | J51: 14.9 | K51: Estimado | L51: 13.9 | M51: =IFERROR(L51*(1-Premissas!$B$5)*(1-Premissas!$B$6)-H51-Premissas!$B$7,"") -> 7.0951722 | N51: =IFERROR(M51/L51,"") -> 0.51044404 | O51: =IFERROR(L51*(1-Premissas!$B$8)-Premissas!$B$9-H51-Premissas!$B$7,"") -> 0.0042222222 | P51: =IFERROR(L51*(1-Premissas!$B$10)-Premissas!$B$11-H51-Premissas!$B$7,"") -> 1.1422222 | Q51: =IFERROR(M51*F51,"") -> 127.7131 | R51: =IFERROR(IF(M51>0,ROUNDUP(Premissas!$B$12/M51,0),"sem lucro"),"") -> 141 | S51: Opcional | T51: N | U51: Caixa com 18 | V51: =IF(AND(T51="S",ISNUMBER(L51),ISNUMBER(F51)),L51*F51*X51,0) -> 0 | W51: =IF(AND(T51="S",ISNUMBER(Q51)),Q51*X51,0) -> 0 | X51: 1 | Y51: =IF(AND(T51="S",ISNUMBER(G51)),G51*X51,0) -> 0
A52: P51 | B52: Pó Solto Translúcido Soft Sheer | C52: Alleva | D52: Maquiagem – Rosto | E52: 4 | F52: 18 | G52: 89.6 | H52: =IF(ISNUMBER(G52),IFERROR(G52/F52,""),"") -> 4.9777778 | I52: 12.9 | J52: 14.9 | K52: Estimado | L52: 13.9 | M52: =IFERROR(L52*(1-Premissas!$B$5)*(1-Premissas!$B$6)-H52-Premissas!$B$7,"") -> 7.0951722 | N52: =IFERROR(M52/L52,"") -> 0.51044404 | O52: =IFERROR(L52*(1-Premissas!$B$8)-Premissas!$B$9-H52-Premissas!$B$7,"") -> 0.0042222222 | P52: =IFERROR(L52*(1-Premissas!$B$10)-Premissas!$B$11-H52-Premissas!$B$7,"") -> 1.1422222 | Q52: =IFERROR(M52*F52,"") -> 127.7131 | R52: =IFERROR(IF(M52>0,ROUNDUP(Premissas!$B$12/M52,0),"sem lucro"),"") -> 141 | S52: Opcional | T52: N | U52: Caixa com 18 | V52: =IF(AND(T52="S",ISNUMBER(L52),ISNUMBER(F52)),L52*F52*X52,0) -> 0 | W52: =IF(AND(T52="S",ISNUMBER(Q52)),Q52*X52,0) -> 0 | X52: 1 | Y52: =IF(AND(T52="S",ISNUMBER(G52)),G52*X52,0) -> 0
A53: P52 | B53: Body Splash 120ml femininos (7 fragrâncias) | C53: Natuza | D53: Perfumaria | E53: 4 | F53: 1 | G53: 6.8 | H53: =IF(ISNUMBER(G53),IFERROR(G53/F53,""),"") -> 6.8 | I53: 19.9 | J53: 29.9 | K53: Estimado | L53: 24.9 | M53: =IFERROR(L53*(1-Premissas!$B$5)*(1-Premissas!$B$6)-H53-Premissas!$B$7,"") -> 15.61845 | N53: =IFERROR(M53/L53,"") -> 0.62724699 | O53: =IFERROR(L53*(1-Premissas!$B$8)-Premissas!$B$9-H53-Premissas!$B$7,"") -> 7.862 | P53: =IFERROR(L53*(1-Premissas!$B$10)-Premissas!$B$11-H53-Premissas!$B$7,"") -> 8.12 | Q53: =IFERROR(M53*F53,"") -> 15.61845 | R53: =IFERROR(IF(M53>0,ROUNDUP(Premissas!$B$12/M53,0),"sem lucro"),"") -> 65 | S53: Comprar | T53: S | U53: Obsession Pink, Libertad, Sahar Al Noor, Royal Rose, Golden Vip, Yara Zahra, Good Angel. Body splash árabe de 200ml de outras marcas sai por ~R$ 59,90 | V53: =IF(AND(T53="S",ISNUMBER(L53),ISNUMBER(F53)),L53*F53*X53,0) -> 298.8 | W53: =IF(AND(T53="S",ISNUMBER(Q53)),Q53*X53,0) -> 187.4214 | X53: 12 | Y53: =IF(AND(T53="S",ISNUMBER(G53)),G53*X53,0) -> 81.6
A54: P53 | B54: Body Splash For Men 120ml (3 fragrâncias) | C54: Natuza | D54: Perfumaria | E54: 4 | F54: 1 | G54: 6.8 | H54: =IF(ISNUMBER(G54),IFERROR(G54/F54,""),"") -> 6.8 | I54: 19.9 | J54: 29.9 | K54: Estimado | L54: 24.9 | M54: =IFERROR(L54*(1-Premissas!$B$5)*(1-Premissas!$B$6)-H54-Premissas!$B$7,"") -> 15.61845 | N54: =IFERROR(M54/L54,"") -> 0.62724699 | O54: =IFERROR(L54*(1-Premissas!$B$8)-Premissas!$B$9-H54-Premissas!$B$7,"") -> 7.862 | P54: =IFERROR(L54*(1-Premissas!$B$10)-Premissas!$B$11-H54-Premissas!$B$7,"") -> 8.12 | Q54: =IFERROR(M54*F54,"") -> 15.61845 | R54: =IFERROR(IF(M54>0,ROUNDUP(Premissas!$B$12/M54,0),"sem lucro"),"") -> 65 | S54: Comprar | T54: S | U54: Asad Black, Royal Black, Hayat Al Gold | V54: =IF(AND(T54="S",ISNUMBER(L54),ISNUMBER(F54)),L54*F54*X54,0) -> 298.8 | W54: =IF(AND(T54="S",ISNUMBER(Q54)),Q54*X54,0) -> 187.4214 | X54: 12 | Y54: =IF(AND(T54="S",ISNUMBER(G54)),G54*X54,0) -> 81.6
A55: P54 | B55: Hidratante Body Cream 120ml (4 fragrâncias) | C55: Natuza | D55: Corpo | E55: 4 | F55: 1 | G55: 6.6 | H55: =IF(ISNUMBER(G55),IFERROR(G55/F55,""),"") -> 6.6 | I55: 19.9 | J55: 24.9 | K55: Estimado | L55: 22.9 | M55: =IFERROR(L55*(1-Premissas!$B$5)*(1-Premissas!$B$6)-H55-Premissas!$B$7,"") -> 13.93745 | N55: =IFERROR(M55/L55,"") -> 0.60862227 | O55: =IFERROR(L55*(1-Premissas!$B$8)-Premissas!$B$9-H55-Premissas!$B$7,"") -> 6.302 | P55: =IFERROR(L55*(1-Premissas!$B$10)-Premissas!$B$11-H55-Premissas!$B$7,"") -> 6.72 | Q55: =IFERROR(M55*F55,"") -> 13.93745 | R55: =IFERROR(IF(M55>0,ROUNDUP(Premissas!$B$12/M55,0),"sem lucro"),"") -> 72 | S55: Comprar (kit Perfumada) | T55: S | U55: Libertad, Obsession Pink, Good Angel, Golden Vip (lote 5) | V55: =IF(AND(T55="S",ISNUMBER(L55),ISNUMBER(F55)),L55*F55*X55,0) -> 274.8 | W55: =IF(AND(T55="S",ISNUMBER(Q55)),Q55*X55,0) -> 167.2494 | X55: 12 | Y55: =IF(AND(T55="S",ISNUMBER(G55)),G55*X55,0) -> 79.2
A56: P55 | B56: Pó Solto Blindagem Fix All | C56: Alleva | D56: Maquiagem – Rosto | E56: 5 | F56: 18 | G56: 89.6 | H56: =IF(ISNUMBER(G56),IFERROR(G56/F56,""),"") -> 4.9777778 | I56: 12.9 | J56: 14.9 | K56: Estimado | L56: 13.9 | M56: =IFERROR(L56*(1-Premissas!$B$5)*(1-Premissas!$B$6)-H56-Premissas!$B$7,"") -> 7.0951722 | N56: =IFERROR(M56/L56,"") -> 0.51044404 | O56: =IFERROR(L56*(1-Premissas!$B$8)-Premissas!$B$9-H56-Premissas!$B$7,"") -> 0.0042222222 | P56: =IFERROR(L56*(1-Premissas!$B$10)-Premissas!$B$11-H56-Premissas!$B$7,"") -> 1.1422222 | Q56: =IFERROR(M56*F56,"") -> 127.7131 | R56: =IFERROR(IF(M56>0,ROUNDUP(Premissas!$B$12/M56,0),"sem lucro"),"") -> 141 | S56: Opcional | T56: N | U56: Caixa com 18 | V56: =IF(AND(T56="S",ISNUMBER(L56),ISNUMBER(F56)),L56*F56*X56,0) -> 0 | W56: =IF(AND(T56="S",ISNUMBER(Q56)),Q56*X56,0) -> 0 | X56: 1 | Y56: =IF(AND(T56="S",ISNUMBER(G56)),G56*X56,0) -> 0
A57: P56 | B57: Trio de Sombras Snow | C57: Mia Make | D57: Maquiagem – Olhos | E57: 5 | F57: 24 | G57: 160.2 | H57: =IF(ISNUMBER(G57),IFERROR(G57/F57,""),"") -> 6.675 | I57: 10 | J57: 14.9 | K57: Estimado | L57: 14.9 | M57: =IFERROR(L57*(1-Premissas!$B$5)*(1-Premissas!$B$6)-H57-Premissas!$B$7,"") -> 6.33845 | N57: =IFERROR(M57/L57,"") -> 0.42539933 | O57: =IFERROR(L57*(1-Premissas!$B$8)-Premissas!$B$9-H57-Premissas!$B$7,"") -> -0.813 | P57: =IFERROR(L57*(1-Premissas!$B$10)-Premissas!$B$11-H57-Premissas!$B$7,"") -> 0.245 | Q57: =IFERROR(M57*F57,"") -> 152.1228 | R57: =IFERROR(IF(M57>0,ROUNDUP(Premissas!$B$12/M57,0),"sem lucro"),"") -> 158 | S57: Opcional | T57: N | V57: =IF(AND(T57="S",ISNUMBER(L57),ISNUMBER(F57)),L57*F57*X57,0) -> 0 | W57: =IF(AND(T57="S",ISNUMBER(Q57)),Q57*X57,0) -> 0 | X57: 1 | Y57: =IF(AND(T57="S",ISNUMBER(G57)),G57*X57,0) -> 0
A58: P57 | B58: Duo Lips Contorno e Batom | C58: Mia Make | D58: Maquiagem – Lábios | E58: 5 | F58: 24 | G58: 165.99 | H58: =IF(ISNUMBER(G58),IFERROR(G58/F58,""),"") -> 6.91625 | I58: 12.9 | J58: 14.9 | K58: Estimado | L58: 14.9 | M58: =IFERROR(L58*(1-Premissas!$B$5)*(1-Premissas!$B$6)-H58-Premissas!$B$7,"") -> 6.0972 | N58: =IFERROR(M58/L58,"") -> 0.40920805 | O58: =IFERROR(L58*(1-Premissas!$B$8)-Premissas!$B$9-H58-Premissas!$B$7,"") -> -1.05425 | P58: =IFERROR(L58*(1-Premissas!$B$10)-Premissas!$B$11-H58-Premissas!$B$7,"") -> 0.00375 | Q58: =IFERROR(M58*F58,"") -> 146.3328 | R58: =IFERROR(IF(M58>0,ROUNDUP(Premissas!$B$12/M58,0),"sem lucro"),"") -> 165 | S58: Opcional | T58: N | U58: Duas coleções de cores no site | V58: =IF(AND(T58="S",ISNUMBER(L58),ISNUMBER(F58)),L58*F58*X58,0) -> 0 | W58: =IF(AND(T58="S",ISNUMBER(Q58)),Q58*X58,0) -> 0 | X58: 1 | Y58: =IF(AND(T58="S",ISNUMBER(G58)),G58*X58,0) -> 0
A59: P58 | B59: Primer Hidratante Hidro 45ml (CS6372) | C59: Pink 21 | D59: Maquiagem – Rosto | E59: 5 | F59: 1 | G59: 6.7 | H59: =IF(ISNUMBER(G59),IFERROR(G59/F59,""),"") -> 6.7 | I59: 12.9 | J59: 16.9 | K59: Estimado | L59: 14.9 | M59: =IFERROR(L59*(1-Premissas!$B$5)*(1-Premissas!$B$6)-H59-Premissas!$B$7,"") -> 6.31345 | N59: =IFERROR(M59/L59,"") -> 0.42372148 | O59: =IFERROR(L59*(1-Premissas!$B$8)-Premissas!$B$9-H59-Premissas!$B$7,"") -> -0.838 | P59: =IFERROR(L59*(1-Premissas!$B$10)-Premissas!$B$11-H59-Premissas!$B$7,"") -> 0.22 | Q59: =IFERROR(M59*F59,"") -> 6.31345 | R59: =IFERROR(IF(M59>0,ROUNDUP(Premissas!$B$12/M59,0),"sem lucro"),"") -> 159 | S59: Comprar (kit Make Completa) | T59: S | V59: =IF(AND(T59="S",ISNUMBER(L59),ISNUMBER(F59)),L59*F59*X59,0) -> 178.8 | W59: =IF(AND(T59="S",ISNUMBER(Q59)),Q59*X59,0) -> 75.7614 | X59: 12 | Y59: =IF(AND(T59="S",ISNUMBER(G59)),G59*X59,0) -> 80.4
A60: P59 | B60: Corretivo Líquido Amora | C60: Pink 21 | D60: Maquiagem – Rosto | E60: 5 | F60: 24 | G60: 161.7 | H60: =IF(ISNUMBER(G60),IFERROR(G60/F60,""),"") -> 6.7375 | I60: 12.9 | J60: 13.29 | K60: Estimado | L60: 12.9 | M60: =IFERROR(L60*(1-Premissas!$B$5)*(1-Premissas!$B$6)-H60-Premissas!$B$7,"") -> 4.39495 | N60: =IFERROR(M60/L60,"") -> 0.3406938 | O60: =IFERROR(L60*(1-Premissas!$B$8)-Premissas!$B$9-H60-Premissas!$B$7,"") -> -2.6355 | P60: =IFERROR(L60*(1-Premissas!$B$10)-Premissas!$B$11-H60-Premissas!$B$7,"") -> -1.4175 | Q60: =IFERROR(M60*F60,"") -> 105.4788 | R60: =IFERROR(IF(M60>0,ROUNDUP(Premissas!$B$12/M60,0),"sem lucro"),"") -> 228 | S60: Opcional | T60: N | U60: Referência: base Amora by Pink 21 R$ 13,29 | V60: =IF(AND(T60="S",ISNUMBER(L60),ISNUMBER(F60)),L60*F60*X60,0) -> 0 | W60: =IF(AND(T60="S",ISNUMBER(Q60)),Q60*X60,0) -> 0 | X60: 1 | Y60: =IF(AND(T60="S",ISNUMBER(G60)),G60*X60,0) -> 0
A61: P60 | B61: Blush em Bastão Amora | C61: Pink 21 | D61: Maquiagem – Rosto | E61: 5 | F61: 24 | G61: 138.99 | H61: =IF(ISNUMBER(G61),IFERROR(G61/F61,""),"") -> 5.79125 | I61: 14.9 | J61: 18.5 | K61: Estimado | L61: 14.9 | M61: =IFERROR(L61*(1-Premissas!$B$5)*(1-Premissas!$B$6)-H61-Premissas!$B$7,"") -> 7.2222 | N61: =IFERROR(M61/L61,"") -> 0.48471141 | O61: =IFERROR(L61*(1-Premissas!$B$8)-Premissas!$B$9-H61-Premissas!$B$7,"") -> 0.07075 | P61: =IFERROR(L61*(1-Premissas!$B$10)-Premissas!$B$11-H61-Premissas!$B$7,"") -> 1.12875 | Q61: =IFERROR(M61*F61,"") -> 173.3328 | R61: =IFERROR(IF(M61>0,ROUNDUP(Premissas!$B$12/M61,0),"sem lucro"),"") -> 139 | S61: Comprar | T61: S | U61: Referência: blush em bastão Pink 21 R$ 18,50 | V61: =IF(AND(T61="S",ISNUMBER(L61),ISNUMBER(F61)),L61*F61*X61,0) -> 357.6 | W61: =IF(AND(T61="S",ISNUMBER(Q61)),Q61*X61,0) -> 173.3328 | X61: 1 | Y61: =IF(AND(T61="S",ISNUMBER(G61)),G61*X61,0) -> 138.99
A62: P61 | B62: Lip Gloss Candy Bear | C62: Pink 21 | D62: Maquiagem – Lábios | E62: 5 | F62: 24 | G62: 191.2 | H62: =IF(ISNUMBER(G62),IFERROR(G62/F62,""),"") -> 7.9666667 | I62: 12.9 | J62: 14.9 | K62: Estimado | L62: 14.9 | M62: =IFERROR(L62*(1-Premissas!$B$5)*(1-Premissas!$B$6)-H62-Premissas!$B$7,"") -> 5.0467833 | N62: =IFERROR(M62/L62,"") -> 0.33871029 | O62: =IFERROR(L62*(1-Premissas!$B$8)-Premissas!$B$9-H62-Premissas!$B$7,"") -> -2.1046667 | P62: =IFERROR(L62*(1-Premissas!$B$10)-Premissas!$B$11-H62-Premissas!$B$7,"") -> -1.0466667 | Q62: =IFERROR(M62*F62,"") -> 121.1228 | R62: =IFERROR(IF(M62>0,ROUNDUP(Premissas!$B$12/M62,0),"sem lucro"),"") -> 199 | S62: Evitar (muitos gloss) | T62: N | V62: =IF(AND(T62="S",ISNUMBER(L62),ISNUMBER(F62)),L62*F62*X62,0) -> 0 | W62: =IF(AND(T62="S",ISNUMBER(Q62)),Q62*X62,0) -> 0 | X62: 1 | Y62: =IF(AND(T62="S",ISNUMBER(G62)),G62*X62,0) -> 0
A63: P62 | B63: Corretivo Quick Fix We Candy Box A | C63: We Candy | D63: Maquiagem – Rosto | E63: 5 | F63: 36 | G63: 224.9 | H63: =IF(ISNUMBER(G63),IFERROR(G63/F63,""),"") -> 6.2472222 | I63: 12.9 | J63: 12.9 | K63: Estimado | L63: 12.9 | M63: =IFERROR(L63*(1-Premissas!$B$5)*(1-Premissas!$B$6)-H63-Premissas!$B$7,"") -> 4.8852278 | N63: =IFERROR(M63/L63,"") -> 0.37869983 | O63: =IFERROR(L63*(1-Premissas!$B$8)-Premissas!$B$9-H63-Premissas!$B$7,"") -> -2.1452222 | P63: =IFERROR(L63*(1-Premissas!$B$10)-Premissas!$B$11-H63-Premissas!$B$7,"") -> -0.92722222 | Q63: =IFERROR(M63*F63,"") -> 175.8682 | R63: =IFERROR(IF(M63>0,ROUNDUP(Premissas!$B$12/M63,0),"sem lucro"),"") -> 205 | S63: Opcional | T63: N | U63: Caixa com 36 | V63: =IF(AND(T63="S",ISNUMBER(L63),ISNUMBER(F63)),L63*F63*X63,0) -> 0 | W63: =IF(AND(T63="S",ISNUMBER(Q63)),Q63*X63,0) -> 0 | X63: 1 | Y63: =IF(AND(T63="S",ISNUMBER(G63)),G63*X63,0) -> 0
A64: P63 | B64: Lip Gloss Fruits (3326.1.1) | C64: Vivai | D64: Maquiagem – Lábios | E64: 5 | F64: 36 | G64: 224.9 | H64: =IF(ISNUMBER(G64),IFERROR(G64/F64,""),"") -> 6.2472222 | I64: 2.08 | J64: 12.9 | K64: Confirmado | L64: 11.9 | M64: =IFERROR(L64*(1-Premissas!$B$5)*(1-Premissas!$B$6)-H64-Premissas!$B$7,"") -> 3.9447278 | N64: =IFERROR(M64/L64,"") -> 0.33148973 | O64: =IFERROR(L64*(1-Premissas!$B$8)-Premissas!$B$9-H64-Premissas!$B$7,"") -> -3.0252222 | P64: =IFERROR(L64*(1-Premissas!$B$10)-Premissas!$B$11-H64-Premissas!$B$7,"") -> -1.7272222 | Q64: =IFERROR(M64*F64,"") -> 142.0102 | R64: =IFERROR(IF(M64>0,ROUNDUP(Premissas!$B$12/M64,0),"sem lucro"),"") -> 254 | S64: Evitar (vendido barato) | T64: N | U64: Box de 24 visto por R$ 49,90 na Amazon (~R$ 2,08/un.) | V64: =IF(AND(T64="S",ISNUMBER(L64),ISNUMBER(F64)),L64*F64*X64,0) -> 0 | W64: =IF(AND(T64="S",ISNUMBER(Q64)),Q64*X64,0) -> 0 | X64: 1 | Y64: =IF(AND(T64="S",ISNUMBER(G64)),G64*X64,0) -> 0
A65: P64 | B65: Gloss Glitter Choko (3429.1.1) | C65: Vivai | D65: Maquiagem – Lábios | E65: 5 | F65: 36 | G65: 229.99 | H65: =IF(ISNUMBER(G65),IFERROR(G65/F65,""),"") -> 6.3886111 | I65: 12.9 | J65: 12.9 | K65: Estimado | L65: 12.9 | M65: =IFERROR(L65*(1-Premissas!$B$5)*(1-Premissas!$B$6)-H65-Premissas!$B$7,"") -> 4.7438389 | N65: =IFERROR(M65/L65,"") -> 0.36773945 | O65: =IFERROR(L65*(1-Premissas!$B$8)-Premissas!$B$9-H65-Premissas!$B$7,"") -> -2.2866111 | P65: =IFERROR(L65*(1-Premissas!$B$10)-Premissas!$B$11-H65-Premissas!$B$7,"") -> -1.0686111 | Q65: =IFERROR(M65*F65,"") -> 170.7782 | R65: =IFERROR(IF(M65>0,ROUNDUP(Premissas!$B$12/M65,0),"sem lucro"),"") -> 211 | S65: Evitar (muitos gloss) | T65: N | U65: Caixa com 36 | V65: =IF(AND(T65="S",ISNUMBER(L65),ISNUMBER(F65)),L65*F65*X65,0) -> 0 | W65: =IF(AND(T65="S",ISNUMBER(Q65)),Q65*X65,0) -> 0 | X65: 1 | Y65: =IF(AND(T65="S",ISNUMBER(G65)),G65*X65,0) -> 0
A66: P65 | B66: Corretivo Líquido Acabamento Matte | C66: Pink 21 | D66: Maquiagem – Rosto | E66: 5 | F66: 24 | G66: 158.8 | H66: =IF(ISNUMBER(G66),IFERROR(G66/F66,""),"") -> 6.6166667 | I66: 12.9 | J66: 12.9 | K66: Estimado | L66: 12.9 | M66: =IFERROR(L66*(1-Premissas!$B$5)*(1-Premissas!$B$6)-H66-Premissas!$B$7,"") -> 4.5157833 | N66: =IFERROR(M66/L66,"") -> 0.35006072 | O66: =IFERROR(L66*(1-Premissas!$B$8)-Premissas!$B$9-H66-Premissas!$B$7,"") -> -2.5146667 | P66: =IFERROR(L66*(1-Premissas!$B$10)-Premissas!$B$11-H66-Premissas!$B$7,"") -> -1.2966667 | Q66: =IFERROR(M66*F66,"") -> 108.3788 | R66: =IFERROR(IF(M66>0,ROUNDUP(Premissas!$B$12/M66,0),"sem lucro"),"") -> 222 | S66: Confirmar qtd | T66: N | U66: Qtd na caixa cortada no print: considerei 24, confirmar | V66: =IF(AND(T66="S",ISNUMBER(L66),ISNUMBER(F66)),L66*F66*X66,0) -> 0 | W66: =IF(AND(T66="S",ISNUMBER(Q66)),Q66*X66,0) -> 0 | X66: 1 | Y66: =IF(AND(T66="S",ISNUMBER(G66)),G66*X66,0) -> 0
A67: P66 | B67: Contorno em Bastão Color Contour | C67: Pink 21 | D67: Maquiagem – Rosto | E67: 5 | F67: 48 | G67: 115.99 | H67: =IF(ISNUMBER(G67),IFERROR(G67/F67,""),"") -> 2.4164583 | I67: 6.76 | J67: 15.9 | K67: Confirmado | L67: 12.9 | M67: =IFERROR(L67*(1-Premissas!$B$5)*(1-Premissas!$B$6)-H67-Premissas!$B$7,"") -> 8.7159917 | N67: =IFERROR(M67/L67,"") -> 0.67565827 | O67: =IFERROR(L67*(1-Premissas!$B$8)-Premissas!$B$9-H67-Premissas!$B$7,"") -> 1.6855417 | P67: =IFERROR(L67*(1-Premissas!$B$10)-Premissas!$B$11-H67-Premissas!$B$7,"") -> 2.9035417 | Q67: =IFERROR(M67*F67,"") -> 418.3676 | R67: =IFERROR(IF(M67>0,ROUNDUP(Premissas!$B$12/M67,0),"sem lucro"),"") -> 115 | S67: Comprar | T67: S | U67: Caixa com 48: custo muito baixo | V67: =IF(AND(T67="S",ISNUMBER(L67),ISNUMBER(F67)),L67*F67*X67,0) -> 619.2 | W67: =IF(AND(T67="S",ISNUMBER(Q67)),Q67*X67,0) -> 418.3676 | X67: 1 | Y67: =IF(AND(T67="S",ISNUMBER(G67)),G67*X67,0) -> 115.99
A68: P67 | B68: Máscara Incolor para Sobrancelha Honey | C68: Pink 21 | D68: Maquiagem – Sobrancelhas | E68: 5 | F68: 24 | G68: 158.8 | H68: =IF(ISNUMBER(G68),IFERROR(G68/F68,""),"") -> 6.6166667 | I68: 12.9 | J68: 12.9 | K68: Estimado | L68: 12.9 | M68: =IFERROR(L68*(1-Premissas!$B$5)*(1-Premissas!$B$6)-H68-Premissas!$B$7,"") -> 4.5157833 | N68: =IFERROR(M68/L68,"") -> 0.35006072 | O68: =IFERROR(L68*(1-Premissas!$B$8)-Premissas!$B$9-H68-Premissas!$B$7,"") -> -2.5146667 | P68: =IFERROR(L68*(1-Premissas!$B$10)-Premissas!$B$11-H68-Premissas!$B$7,"") -> -1.2966667 | Q68: =IFERROR(M68*F68,"") -> 108.3788 | R68: =IFERROR(IF(M68>0,ROUNDUP(Premissas!$B$12/M68,0),"sem lucro"),"") -> 222 | S68: Confirmar qtd | T68: N | U68: Qtd na caixa cortada no print: considerei 24, confirmar | V68: =IF(AND(T68="S",ISNUMBER(L68),ISNUMBER(F68)),L68*F68*X68,0) -> 0 | W68: =IF(AND(T68="S",ISNUMBER(Q68)),Q68*X68,0) -> 0 | X68: 1 | Y68: =IF(AND(T68="S",ISNUMBER(G68)),G68*X68,0) -> 0
A69: P68 | B69: Lip Gloss Amora (CS7043) | C69: Pink 21 | D69: Maquiagem – Lábios | E69: 5 | F69: 24 | G69: 161.7 | H69: =IF(ISNUMBER(G69),IFERROR(G69/F69,""),"") -> 6.7375 | I69: 12.9 | J69: 12.9 | K69: Estimado | L69: 12.9 | M69: =IFERROR(L69*(1-Premissas!$B$5)*(1-Premissas!$B$6)-H69-Premissas!$B$7,"") -> 4.39495 | N69: =IFERROR(M69/L69,"") -> 0.3406938 | O69: =IFERROR(L69*(1-Premissas!$B$8)-Premissas!$B$9-H69-Premissas!$B$7,"") -> -2.6355 | P69: =IFERROR(L69*(1-Premissas!$B$10)-Premissas!$B$11-H69-Premissas!$B$7,"") -> -1.4175 | Q69: =IFERROR(M69*F69,"") -> 105.4788 | R69: =IFERROR(IF(M69>0,ROUNDUP(Premissas!$B$12/M69,0),"sem lucro"),"") -> 228 | S69: Evitar (muitos gloss) | T69: N | V69: =IF(AND(T69="S",ISNUMBER(L69),ISNUMBER(F69)),L69*F69*X69,0) -> 0 | W69: =IF(AND(T69="S",ISNUMBER(Q69)),Q69*X69,0) -> 0 | X69: 1 | Y69: =IF(AND(T69="S",ISNUMBER(G69)),G69*X69,0) -> 0
A70: P69 | B70: Blush Líquido The Pink Multiuso | C70: Pink 21 | D70: Maquiagem – Rosto | E70: 5 | F70: 24 | G70: 158.8 | H70: =IF(ISNUMBER(G70),IFERROR(G70/F70,""),"") -> 6.6166667 | I70: 19.9 | J70: 21.7 | K70: Confirmado | L70: 17.9 | M70: =IFERROR(L70*(1-Premissas!$B$5)*(1-Premissas!$B$6)-H70-Premissas!$B$7,"") -> 9.2182833 | N70: =IFERROR(M70/L70,"") -> 0.5149879 | O70: =IFERROR(L70*(1-Premissas!$B$8)-Premissas!$B$9-H70-Premissas!$B$7,"") -> 1.8853333 | P70: =IFERROR(L70*(1-Premissas!$B$10)-Premissas!$B$11-H70-Premissas!$B$7,"") -> 2.7033333 | Q70: =IFERROR(M70*F70,"") -> 221.2388 | R70: =IFERROR(IF(M70>0,ROUNDUP(Premissas!$B$12/M70,0),"sem lucro"),"") -> 109 | S70: Comprar | T70: S | U70: Blush e batom; em alta | V70: =IF(AND(T70="S",ISNUMBER(L70),ISNUMBER(F70)),L70*F70*X70,0) -> 429.6 | W70: =IF(AND(T70="S",ISNUMBER(Q70)),Q70*X70,0) -> 221.2388 | X70: 1 | Y70: =IF(AND(T70="S",ISNUMBER(G70)),G70*X70,0) -> 158.8
A71: P70 | B71: Delineador Líquido Peel Off Amora | C71: Pink 21 | D71: Maquiagem – Olhos | E71: 5 | F71: 24 | G71: 126.4 | H71: =IF(ISNUMBER(G71),IFERROR(G71/F71,""),"") -> 5.2666667 | I71: 12.9 | J71: 12.9 | K71: Estimado | L71: 12.9 | M71: =IFERROR(L71*(1-Premissas!$B$5)*(1-Premissas!$B$6)-H71-Premissas!$B$7,"") -> 5.8657833 | N71: =IFERROR(M71/L71,"") -> 0.45471189 | O71: =IFERROR(L71*(1-Premissas!$B$8)-Premissas!$B$9-H71-Premissas!$B$7,"") -> -1.1646667 | P71: =IFERROR(L71*(1-Premissas!$B$10)-Premissas!$B$11-H71-Premissas!$B$7,"") -> 0.053333333 | Q71: =IFERROR(M71*F71,"") -> 140.7788 | R71: =IFERROR(IF(M71>0,ROUNDUP(Premissas!$B$12/M71,0),"sem lucro"),"") -> 171 | S71: Opcional | T71: N | V71: =IF(AND(T71="S",ISNUMBER(L71),ISNUMBER(F71)),L71*F71*X71,0) -> 0 | W71: =IF(AND(T71="S",ISNUMBER(Q71)),Q71*X71,0) -> 0 | X71: 1 | Y71: =IF(AND(T71="S",ISNUMBER(G71)),G71*X71,0) -> 0
A72: P71 | B72: Lip Balm (CS7085) | C72: Pink 21 | D72: Maquiagem – Lábios | E72: 5 | F72: 24 | G72: 148.8 | H72: =IF(ISNUMBER(G72),IFERROR(G72/F72,""),"") -> 6.2 | I72: 10 | J72: 12.9 | K72: Estimado | L72: 11.9 | M72: =IFERROR(L72*(1-Premissas!$B$5)*(1-Premissas!$B$6)-H72-Premissas!$B$7,"") -> 3.99195 | N72: =IFERROR(M72/L72,"") -> 0.33545798 | O72: =IFERROR(L72*(1-Premissas!$B$8)-Premissas!$B$9-H72-Premissas!$B$7,"") -> -2.978 | P72: =IFERROR(L72*(1-Premissas!$B$10)-Premissas!$B$11-H72-Premissas!$B$7,"") -> -1.68 | Q72: =IFERROR(M72*F72,"") -> 95.8068 | R72: =IFERROR(IF(M72>0,ROUNDUP(Premissas!$B$12/M72,0),"sem lucro"),"") -> 251 | S72: Opcional | T72: N | V72: =IF(AND(T72="S",ISNUMBER(L72),ISNUMBER(F72)),L72*F72*X72,0) -> 0 | W72: =IF(AND(T72="S",ISNUMBER(Q72)),Q72*X72,0) -> 0 | X72: 1 | Y72: =IF(AND(T72="S",ISNUMBER(G72)),G72*X72,0) -> 0
A73: P72 | B73: Paleta de Sombras The Iconic (Cor 01 e Cor 03) | C73: Pink 21 | D73: Maquiagem – Olhos | E73: 5 | F73: 1 | G73: 6.8 | H73: =IF(ISNUMBER(G73),IFERROR(G73/F73,""),"") -> 6.8 | I73: 11.99 | J73: 45.9 | K73: Estimado | L73: 19.9 | M73: =IFERROR(L73*(1-Premissas!$B$5)*(1-Premissas!$B$6)-H73-Premissas!$B$7,"") -> 10.91595 | N73: =IFERROR(M73/L73,"") -> 0.5485402 | O73: =IFERROR(L73*(1-Premissas!$B$8)-Premissas!$B$9-H73-Premissas!$B$7,"") -> 3.462 | P73: =IFERROR(L73*(1-Premissas!$B$10)-Premissas!$B$11-H73-Premissas!$B$7,"") -> 4.12 | Q73: =IFERROR(M73*F73,"") -> 10.91595 | R73: =IFERROR(IF(M73>0,ROUNDUP(Premissas!$B$12/M73,0),"sem lucro"),"") -> 92 | S73: Comprar | T73: S | U73: 9 cores. Cor 03 no lote 6, mesmo preço. Outras paletas Pink 21 de R$ 11,99 a R$ 45,90 | V73: =IF(AND(T73="S",ISNUMBER(L73),ISNUMBER(F73)),L73*F73*X73,0) -> 238.8 | W73: =IF(AND(T73="S",ISNUMBER(Q73)),Q73*X73,0) -> 130.9914 | X73: 12 | Y73: =IF(AND(T73="S",ISNUMBER(G73)),G73*X73,0) -> 81.6
A74: P73 | B74: Corretivo Líquido (CS5963) | C74: Pink 21 | D74: Maquiagem – Rosto | E74: 6 | F74: 24 | G74: 93.99 | H74: =IF(ISNUMBER(G74),IFERROR(G74/F74,""),"") -> 3.91625 | I74: 12.9 | J74: 12.9 | K74: Estimado | L74: 12.9 | M74: =IFERROR(L74*(1-Premissas!$B$5)*(1-Premissas!$B$6)-H74-Premissas!$B$7,"") -> 7.2162 | N74: =IFERROR(M74/L74,"") -> 0.55939535 | O74: =IFERROR(L74*(1-Premissas!$B$8)-Premissas!$B$9-H74-Premissas!$B$7,"") -> 0.18575 | P74: =IFERROR(L74*(1-Premissas!$B$10)-Premissas!$B$11-H74-Premissas!$B$7,"") -> 1.40375 | Q74: =IFERROR(M74*F74,"") -> 173.1888 | R74: =IFERROR(IF(M74>0,ROUNDUP(Premissas!$B$12/M74,0),"sem lucro"),"") -> 139 | S74: Comprar (único corretivo) | T74: S | U74: Corretivo mais barato da lista | V74: =IF(AND(T74="S",ISNUMBER(L74),ISNUMBER(F74)),L74*F74*X74,0) -> 309.6 | W74: =IF(AND(T74="S",ISNUMBER(Q74)),Q74*X74,0) -> 173.1888 | X74: 1 | Y74: =IF(AND(T74="S",ISNUMBER(G74)),G74*X74,0) -> 93.99
A75: P74 | B75: Máscara para Cílios Volume e Define | C75: 4Angels | D75: Maquiagem – Olhos | E75: 6 | F75: 24 | G75: 142.9 | H75: =IF(ISNUMBER(G75),IFERROR(G75/F75,""),"") -> 5.9541667 | I75: 10 | J75: 12.9 | K75: Estimado | L75: 11.9 | M75: =IFERROR(L75*(1-Premissas!$B$5)*(1-Premissas!$B$6)-H75-Premissas!$B$7,"") -> 4.2377833 | N75: =IFERROR(M75/L75,"") -> 0.35611625 | O75: =IFERROR(L75*(1-Premissas!$B$8)-Premissas!$B$9-H75-Premissas!$B$7,"") -> -2.7321667 | P75: =IFERROR(L75*(1-Premissas!$B$10)-Premissas!$B$11-H75-Premissas!$B$7,"") -> -1.4341667 | Q75: =IFERROR(M75*F75,"") -> 101.7068 | R75: =IFERROR(IF(M75>0,ROUNDUP(Premissas!$B$12/M75,0),"sem lucro"),"") -> 236 | S75: Confirmar qtd | T75: N | U75: Qtd na caixa cortada no print: considerei 24, confirmar | V75: =IF(AND(T75="S",ISNUMBER(L75),ISNUMBER(F75)),L75*F75*X75,0) -> 0 | W75: =IF(AND(T75="S",ISNUMBER(Q75)),Q75*X75,0) -> 0 | X75: 1 | Y75: =IF(AND(T75="S",ISNUMBER(G75)),G75*X75,0) -> 0
A76: P75 | B76: Batom Líquido (BR1262) | C76: 4Angels | D76: Maquiagem – Lábios | E76: 6 | F76: 24 | G76: 142.9 | H76: =IF(ISNUMBER(G76),IFERROR(G76/F76,""),"") -> 5.9541667 | I76: 10 | J76: 12.9 | K76: Estimado | L76: 11.9 | M76: =IFERROR(L76*(1-Premissas!$B$5)*(1-Premissas!$B$6)-H76-Premissas!$B$7,"") -> 4.2377833 | N76: =IFERROR(M76/L76,"") -> 0.35611625 | O76: =IFERROR(L76*(1-Premissas!$B$8)-Premissas!$B$9-H76-Premissas!$B$7,"") -> -2.7321667 | P76: =IFERROR(L76*(1-Premissas!$B$10)-Premissas!$B$11-H76-Premissas!$B$7,"") -> -1.4341667 | Q76: =IFERROR(M76*F76,"") -> 101.7068 | R76: =IFERROR(IF(M76>0,ROUNDUP(Premissas!$B$12/M76,0),"sem lucro"),"") -> 236 | S76: Evitar (já tem batom) | T76: N | V76: =IF(AND(T76="S",ISNUMBER(L76),ISNUMBER(F76)),L76*F76*X76,0) -> 0 | W76: =IF(AND(T76="S",ISNUMBER(Q76)),Q76*X76,0) -> 0 | X76: 1 | Y76: =IF(AND(T76="S",ISNUMBER(G76)),G76*X76,0) -> 0
A77: P76 | B77: Lip Gloss Caramel (BR1260) | C77: 4Angels | D77: Maquiagem – Lábios | E77: 6 | F77: 24 | G77: 142.9 | H77: =IF(ISNUMBER(G77),IFERROR(G77/F77,""),"") -> 5.9541667 | I77: 10 | J77: 12.9 | K77: Estimado | L77: 11.9 | M77: =IFERROR(L77*(1-Premissas!$B$5)*(1-Premissas!$B$6)-H77-Premissas!$B$7,"") -> 4.2377833 | N77: =IFERROR(M77/L77,"") -> 0.35611625 | O77: =IFERROR(L77*(1-Premissas!$B$8)-Premissas!$B$9-H77-Premissas!$B$7,"") -> -2.7321667 | P77: =IFERROR(L77*(1-Premissas!$B$10)-Premissas!$B$11-H77-Premissas!$B$7,"") -> -1.4341667 | Q77: =IFERROR(M77*F77,"") -> 101.7068 | R77: =IFERROR(IF(M77>0,ROUNDUP(Premissas!$B$12/M77,0),"sem lucro"),"") -> 236 | S77: Evitar (muitos gloss) | T77: N | V77: =IF(AND(T77="S",ISNUMBER(L77),ISNUMBER(F77)),L77*F77*X77,0) -> 0 | W77: =IF(AND(T77="S",ISNUMBER(Q77)),Q77*X77,0) -> 0 | X77: 1 | Y77: =IF(AND(T77="S",ISNUMBER(G77)),G77*X77,0) -> 0
A78: P77 | B78: Lip Tint (BR1255) | C78: 4Angels | D78: Maquiagem – Lábios | E78: 6 | F78: 24 | G78: 131.3 | H78: =IF(ISNUMBER(G78),IFERROR(G78/F78,""),"") -> 5.4708333 | I78: 10 | J78: 10 | K78: Confirmado | L78: 11.9 | M78: =IFERROR(L78*(1-Premissas!$B$5)*(1-Premissas!$B$6)-H78-Premissas!$B$7,"") -> 4.7211167 | N78: =IFERROR(M78/L78,"") -> 0.39673249 | O78: =IFERROR(L78*(1-Premissas!$B$8)-Premissas!$B$9-H78-Premissas!$B$7,"") -> -2.2488333 | P78: =IFERROR(L78*(1-Premissas!$B$10)-Premissas!$B$11-H78-Premissas!$B$7,"") -> -0.95083333 | Q78: =IFERROR(M78*F78,"") -> 113.3068 | R78: =IFERROR(IF(M78>0,ROUNDUP(Premissas!$B$12/M78,0),"sem lucro"),"") -> 212 | S78: Opcional | T78: N | U78: Lip tint 4Angels visto por R$ 10 | V78: =IF(AND(T78="S",ISNUMBER(L78),ISNUMBER(F78)),L78*F78*X78,0) -> 0 | W78: =IF(AND(T78="S",ISNUMBER(Q78)),Q78*X78,0) -> 0 | X78: 1 | Y78: =IF(AND(T78="S",ISNUMBER(G78)),G78*X78,0) -> 0
A79: P78 | B79: Delineador Líquido (BR1250) | C79: 4Angels | D79: Maquiagem – Olhos | E79: 6 | F79: 24 | G79: 113.8 | H79: =IF(ISNUMBER(G79),IFERROR(G79/F79,""),"") -> 4.7416667 | I79: 10 | J79: 12.9 | K79: Estimado | L79: 11.9 | M79: =IFERROR(L79*(1-Premissas!$B$5)*(1-Premissas!$B$6)-H79-Premissas!$B$7,"") -> 5.4502833 | N79: =IFERROR(M79/L79,"") -> 0.458007 | O79: =IFERROR(L79*(1-Premissas!$B$8)-Premissas!$B$9-H79-Premissas!$B$7,"") -> -1.5196667 | P79: =IFERROR(L79*(1-Premissas!$B$10)-Premissas!$B$11-H79-Premissas!$B$7,"") -> -0.22166667 | Q79: =IFERROR(M79*F79,"") -> 130.8068 | R79: =IFERROR(IF(M79>0,ROUNDUP(Premissas!$B$12/M79,0),"sem lucro"),"") -> 184 | S79: Opcional | T79: N | V79: =IF(AND(T79="S",ISNUMBER(L79),ISNUMBER(F79)),L79*F79*X79,0) -> 0 | W79: =IF(AND(T79="S",ISNUMBER(Q79)),Q79*X79,0) -> 0 | X79: 1 | Y79: =IF(AND(T79="S",ISNUMBER(G79)),G79*X79,0) -> 0
A80: P79 | B80: Paleta de Sombras (BR1248) | C80: 4Angels | D80: Maquiagem – Olhos | E80: 6 | F80: 24 | G80: 113.6 | H80: =IF(ISNUMBER(G80),IFERROR(G80/F80,""),"") -> 4.7333333 | I80: 10 | J80: 12.9 | K80: Estimado | L80: 12.9 | M80: =IFERROR(L80*(1-Premissas!$B$5)*(1-Premissas!$B$6)-H80-Premissas!$B$7,"") -> 6.3991167 | N80: =IFERROR(M80/L80,"") -> 0.49605556 | O80: =IFERROR(L80*(1-Premissas!$B$8)-Premissas!$B$9-H80-Premissas!$B$7,"") -> -0.63133333 | P80: =IFERROR(L80*(1-Premissas!$B$10)-Premissas!$B$11-H80-Premissas!$B$7,"") -> 0.58666667 | Q80: =IFERROR(M80*F80,"") -> 153.5788 | R80: =IFERROR(IF(M80>0,ROUNDUP(Premissas!$B$12/M80,0),"sem lucro"),"") -> 157 | S80: Opcional | T80: N | U80: A The Iconic (Pink 21) dá mais lucro | V80: =IF(AND(T80="S",ISNUMBER(L80),ISNUMBER(F80)),L80*F80*X80,0) -> 0 | W80: =IF(AND(T80="S",ISNUMBER(Q80)),Q80*X80,0) -> 0 | X80: 1 | Y80: =IF(AND(T80="S",ISNUMBER(G80)),G80*X80,0) -> 0
A81: P80 | B81: Corretivo Líquido Camuflagem Matte | C81: 4Angels | D81: Maquiagem – Rosto | E81: 7 | F81: 24 | G81: 142.9 | H81: =IF(ISNUMBER(G81),IFERROR(G81/F81,""),"") -> 5.9541667 | I81: 10 | J81: 12.9 | K81: Estimado | L81: 11.9 | M81: =IFERROR(L81*(1-Premissas!$B$5)*(1-Premissas!$B$6)-H81-Premissas!$B$7,"") -> 4.2377833 | N81: =IFERROR(M81/L81,"") -> 0.35611625 | O81: =IFERROR(L81*(1-Premissas!$B$8)-Premissas!$B$9-H81-Premissas!$B$7,"") -> -2.7321667 | P81: =IFERROR(L81*(1-Premissas!$B$10)-Premissas!$B$11-H81-Premissas!$B$7,"") -> -1.4341667 | Q81: =IFERROR(M81*F81,"") -> 101.7068 | R81: =IFERROR(IF(M81>0,ROUNDUP(Premissas!$B$12/M81,0),"sem lucro"),"") -> 236 | S81: Evitar (tem corretivo melhor) | T81: N | U81: Qtd na caixa cortada no print: considerei 24, confirmar | V81: =IF(AND(T81="S",ISNUMBER(L81),ISNUMBER(F81)),L81*F81*X81,0) -> 0 | W81: =IF(AND(T81="S",ISNUMBER(Q81)),Q81*X81,0) -> 0 | X81: 1 | Y81: =IF(AND(T81="S",ISNUMBER(G81)),G81*X81,0) -> 0
A82: P81 | B82: Lip Oil Heart Charm (BR1228) | C82: 4Angels | D82: Maquiagem – Lábios | E82: 7 | F82: 24 | G82: 150.2 | H82: =IF(ISNUMBER(G82),IFERROR(G82/F82,""),"") -> 6.2583333 | I82: 10 | J82: 12.9 | K82: Estimado | L82: 11.9 | M82: =IFERROR(L82*(1-Premissas!$B$5)*(1-Premissas!$B$6)-H82-Premissas!$B$7,"") -> 3.9336167 | N82: =IFERROR(M82/L82,"") -> 0.33055602 | O82: =IFERROR(L82*(1-Premissas!$B$8)-Premissas!$B$9-H82-Premissas!$B$7,"") -> -3.0363333 | P82: =IFERROR(L82*(1-Premissas!$B$10)-Premissas!$B$11-H82-Premissas!$B$7,"") -> -1.7383333 | Q82: =IFERROR(M82*F82,"") -> 94.4068 | R82: =IFERROR(IF(M82>0,ROUNDUP(Premissas!$B$12/M82,0),"sem lucro"),"") -> 255 | S82: Evitar (muitos gloss) | T82: N | V82: =IF(AND(T82="S",ISNUMBER(L82),ISNUMBER(F82)),L82*F82*X82,0) -> 0 | W82: =IF(AND(T82="S",ISNUMBER(Q82)),Q82*X82,0) -> 0 | X82: 1 | Y82: =IF(AND(T82="S",ISNUMBER(G82)),G82*X82,0) -> 0
A83: P82 | B83: Lip Oil (BR1226) | C83: 4Angels | D83: Maquiagem – Lábios | E83: 7 | F83: 24 | G83: 142.9 | H83: =IF(ISNUMBER(G83),IFERROR(G83/F83,""),"") -> 5.9541667 | I83: 10 | J83: 12.9 | K83: Estimado | L83: 11.9 | M83: =IFERROR(L83*(1-Premissas!$B$5)*(1-Premissas!$B$6)-H83-Premissas!$B$7,"") -> 4.2377833 | N83: =IFERROR(M83/L83,"") -> 0.35611625 | O83: =IFERROR(L83*(1-Premissas!$B$8)-Premissas!$B$9-H83-Premissas!$B$7,"") -> -2.7321667 | P83: =IFERROR(L83*(1-Premissas!$B$10)-Premissas!$B$11-H83-Premissas!$B$7,"") -> -1.4341667 | Q83: =IFERROR(M83*F83,"") -> 101.7068 | R83: =IFERROR(IF(M83>0,ROUNDUP(Premissas!$B$12/M83,0),"sem lucro"),"") -> 236 | S83: Evitar (muitos gloss) | T83: N | V83: =IF(AND(T83="S",ISNUMBER(L83),ISNUMBER(F83)),L83*F83*X83,0) -> 0 | W83: =IF(AND(T83="S",ISNUMBER(Q83)),Q83*X83,0) -> 0 | X83: 1 | Y83: =IF(AND(T83="S",ISNUMBER(G83)),G83*X83,0) -> 0
A84: P83 | B84: Lip Gloss (BR1225) | C84: 4Angels | D84: Maquiagem – Lábios | E84: 7 | F84: 24 | G84: 142.9 | H84: =IF(ISNUMBER(G84),IFERROR(G84/F84,""),"") -> 5.9541667 | I84: 10 | J84: 12.9 | K84: Estimado | L84: 11.9 | M84: =IFERROR(L84*(1-Premissas!$B$5)*(1-Premissas!$B$6)-H84-Premissas!$B$7,"") -> 4.2377833 | N84: =IFERROR(M84/L84,"") -> 0.35611625 | O84: =IFERROR(L84*(1-Premissas!$B$8)-Premissas!$B$9-H84-Premissas!$B$7,"") -> -2.7321667 | P84: =IFERROR(L84*(1-Premissas!$B$10)-Premissas!$B$11-H84-Premissas!$B$7,"") -> -1.4341667 | Q84: =IFERROR(M84*F84,"") -> 101.7068 | R84: =IFERROR(IF(M84>0,ROUNDUP(Premissas!$B$12/M84,0),"sem lucro"),"") -> 236 | S84: Evitar (muitos gloss) | T84: N | V84: =IF(AND(T84="S",ISNUMBER(L84),ISNUMBER(F84)),L84*F84*X84,0) -> 0 | W84: =IF(AND(T84="S",ISNUMBER(Q84)),Q84*X84,0) -> 0 | X84: 1 | Y84: =IF(AND(T84="S",ISNUMBER(G84)),G84*X84,0) -> 0
A85: P84 | B85: Brilho Labial Plump Cat Omg | C85: Love Rain | D85: Maquiagem – Lábios | E85: 7 | F85: 1 | G85: 6 | H85: =IF(ISNUMBER(G85),IFERROR(G85/F85,""),"") -> 6 | I85: 12.9 | J85: 12.9 | K85: Estimado | L85: 12.9 | M85: =IFERROR(L85*(1-Premissas!$B$5)*(1-Premissas!$B$6)-H85-Premissas!$B$7,"") -> 5.13245 | N85: =IFERROR(M85/L85,"") -> 0.39786434 | O85: =IFERROR(L85*(1-Premissas!$B$8)-Premissas!$B$9-H85-Premissas!$B$7,"") -> -1.898 | P85: =IFERROR(L85*(1-Premissas!$B$10)-Premissas!$B$11-H85-Premissas!$B$7,"") -> -0.68 | Q85: =IFERROR(M85*F85,"") -> 5.13245 | R85: =IFERROR(IF(M85>0,ROUNDUP(Premissas!$B$12/M85,0),"sem lucro"),"") -> 195 | S85: Opcional | T85: N | V85: =IF(AND(T85="S",ISNUMBER(L85),ISNUMBER(F85)),L85*F85*X85,0) -> 0 | W85: =IF(AND(T85="S",ISNUMBER(Q85)),Q85*X85,0) -> 0 | X85: 12 | Y85: =IF(AND(T85="S",ISNUMBER(G85)),G85*X85,0) -> 0
A86: P85 | B86: Lenço Demaquilante 30 un. (Vit. C, Niacinamida, Retinol, Ác. Hialurônico) | C86: Super Poderes | D86: Skincare | E86: 7 | F86: 1 | G86: 5.2 | H86: =IF(ISNUMBER(G86),IFERROR(G86/F86,""),"") -> 5.2 | I86: 7.99 | J86: 10 | K86: Confirmado | L86: 9.9 | M86: =IFERROR(L86*(1-Premissas!$B$5)*(1-Premissas!$B$6)-H86-Premissas!$B$7,"") -> 3.11095 | N86: =IFERROR(M86/L86,"") -> 0.31423737 | O86: =IFERROR(L86*(1-Premissas!$B$8)-Premissas!$B$9-H86-Premissas!$B$7,"") -> -3.738 | P86: =IFERROR(L86*(1-Premissas!$B$10)-Premissas!$B$11-H86-Premissas!$B$7,"") -> -2.28 | Q86: =IFERROR(M86*F86,"") -> 3.11095 | R86: =IFERROR(IF(M86>0,ROUNDUP(Premissas!$B$12/M86,0),"sem lucro"),"") -> 322 | S86: Opcional (bom para kit) | T86: N | U86: 4 versões, mesmo preço | V86: =IF(AND(T86="S",ISNUMBER(L86),ISNUMBER(F86)),L86*F86*X86,0) -> 0 | W86: =IF(AND(T86="S",ISNUMBER(Q86)),Q86*X86,0) -> 0 | X86: 12 | Y86: =IF(AND(T86="S",ISNUMBER(G86)),G86*X86,0) -> 0
A87: P86 | B87: Corretivo em Bastão | C87: Super Poderes | D87: Maquiagem – Rosto | E87: 7 | F87: 24 | G87: 164.5 | H87: =IF(ISNUMBER(G87),IFERROR(G87/F87,""),"") -> 6.8541667 | I87: 12.9 | J87: 15 | K87: Estimado | L87: 12.9 | M87: =IFERROR(L87*(1-Premissas!$B$5)*(1-Premissas!$B$6)-H87-Premissas!$B$7,"") -> 4.2782833 | N87: =IFERROR(M87/L87,"") -> 0.33164987 | O87: =IFERROR(L87*(1-Premissas!$B$8)-Premissas!$B$9-H87-Premissas!$B$7,"") -> -2.7521667 | P87: =IFERROR(L87*(1-Premissas!$B$10)-Premissas!$B$11-H87-Premissas!$B$7,"") -> -1.5341667 | Q87: =IFERROR(M87*F87,"") -> 102.6788 | R87: =IFERROR(IF(M87>0,ROUNDUP(Premissas!$B$12/M87,0),"sem lucro"),"") -> 234 | S87: Evitar (Color Cover é mais barato) | T87: N | V87: =IF(AND(T87="S",ISNUMBER(L87),ISNUMBER(F87)),L87*F87*X87,0) -> 0 | W87: =IF(AND(T87="S",ISNUMBER(Q87)),Q87*X87,0) -> 0 | X87: 1 | Y87: =IF(AND(T87="S",ISNUMBER(G87)),G87*X87,0) -> 0
A88: P87 | B88: Máscara para Cílios (E-CZ223) | C88: Melana | D88: Maquiagem – Olhos | E88: 7 | F88: 24 | G88: 132.2 | H88: =IF(ISNUMBER(G88),IFERROR(G88/F88,""),"") -> 5.5083333 | I88: 12.9 | J88: 12.9 | K88: Estimado | L88: 12.9 | M88: =IFERROR(L88*(1-Premissas!$B$5)*(1-Premissas!$B$6)-H88-Premissas!$B$7,"") -> 5.6241167 | N88: =IFERROR(M88/L88,"") -> 0.43597804 | O88: =IFERROR(L88*(1-Premissas!$B$8)-Premissas!$B$9-H88-Premissas!$B$7,"") -> -1.4063333 | P88: =IFERROR(L88*(1-Premissas!$B$10)-Premissas!$B$11-H88-Premissas!$B$7,"") -> -0.18833333 | Q88: =IFERROR(M88*F88,"") -> 134.9788 | R88: =IFERROR(IF(M88>0,ROUNDUP(Premissas!$B$12/M88,0),"sem lucro"),"") -> 178 | S88: Opcional | T88: N | V88: =IF(AND(T88="S",ISNUMBER(L88),ISNUMBER(F88)),L88*F88*X88,0) -> 0 | W88: =IF(AND(T88="S",ISNUMBER(Q88)),Q88*X88,0) -> 0 | X88: 1 | Y88: =IF(AND(T88="S",ISNUMBER(G88)),G88*X88,0) -> 0
A89: P88 | B89: Delineador Líquido Boom Eyes | C89: Pink 21 | D89: Maquiagem – Olhos | E89: 7 | F89: 24 | G89: 158.8 | H89: =IF(ISNUMBER(G89),IFERROR(G89/F89,""),"") -> 6.6166667 | I89: 12.9 | J89: 12.9 | K89: Estimado | L89: 12.9 | M89: =IFERROR(L89*(1-Premissas!$B$5)*(1-Premissas!$B$6)-H89-Premissas!$B$7,"") -> 4.5157833 | N89: =IFERROR(M89/L89,"") -> 0.35006072 | O89: =IFERROR(L89*(1-Premissas!$B$8)-Premissas!$B$9-H89-Premissas!$B$7,"") -> -2.5146667 | P89: =IFERROR(L89*(1-Premissas!$B$10)-Premissas!$B$11-H89-Premissas!$B$7,"") -> -1.2966667 | Q89: =IFERROR(M89*F89,"") -> 108.3788 | R89: =IFERROR(IF(M89>0,ROUNDUP(Premissas!$B$12/M89,0),"sem lucro"),"") -> 222 | S89: Opcional | T89: N | V89: =IF(AND(T89="S",ISNUMBER(L89),ISNUMBER(F89)),L89*F89*X89,0) -> 0 | W89: =IF(AND(T89="S",ISNUMBER(Q89)),Q89*X89,0) -> 0 | X89: 1 | Y89: =IF(AND(T89="S",ISNUMBER(G89)),G89*X89,0) -> 0
A90: P89 | B90: Corretivo em Bastão Color Cover | C90: Pink 21 | D90: Maquiagem – Rosto | E90: 7 | F90: 48 | G90: 116.7 | H90: =IF(ISNUMBER(G90),IFERROR(G90/F90,""),"") -> 2.43125 | I90: 13.8 | J90: 15.9 | K90: Confirmado | L90: 12.9 | M90: =IFERROR(L90*(1-Premissas!$B$5)*(1-Premissas!$B$6)-H90-Premissas!$B$7,"") -> 8.7012 | N90: =IFERROR(M90/L90,"") -> 0.67451163 | O90: =IFERROR(L90*(1-Premissas!$B$8)-Premissas!$B$9-H90-Premissas!$B$7,"") -> 1.67075 | P90: =IFERROR(L90*(1-Premissas!$B$10)-Premissas!$B$11-H90-Premissas!$B$7,"") -> 2.88875 | Q90: =IFERROR(M90*F90,"") -> 417.6576 | R90: =IFERROR(IF(M90>0,ROUNDUP(Premissas!$B$12/M90,0),"sem lucro"),"") -> 115 | S90: Comprar | T90: S | U90: Caixa com 48: custo muito baixo. Outros corretivos Pink 21 R$ 13,80–15,90 | V90: =IF(AND(T90="S",ISNUMBER(L90),ISNUMBER(F90)),L90*F90*X90,0) -> 619.2 | W90: =IF(AND(T90="S",ISNUMBER(Q90)),Q90*X90,0) -> 417.6576 | X90: 1 | Y90: =IF(AND(T90="S",ISNUMBER(G90)),G90*X90,0) -> 116.7
A91: P90 | B91: Lip Gloss Honey (CS6661) | C91: Pink 21 | D91: Maquiagem – Lábios | E91: 7 | F91: 24 | G91: 129.6 | H91: =IF(ISNUMBER(G91),IFERROR(G91/F91,""),"") -> 5.4 | I91: 12.9 | J91: 12.9 | K91: Estimado | L91: 12.9 | M91: =IFERROR(L91*(1-Premissas!$B$5)*(1-Premissas!$B$6)-H91-Premissas!$B$7,"") -> 5.73245 | N91: =IFERROR(M91/L91,"") -> 0.44437597 | O91: =IFERROR(L91*(1-Premissas!$B$8)-Premissas!$B$9-H91-Premissas!$B$7,"") -> -1.298 | P91: =IFERROR(L91*(1-Premissas!$B$10)-Premissas!$B$11-H91-Premissas!$B$7,"") -> -0.08 | Q91: =IFERROR(M91*F91,"") -> 137.5788 | R91: =IFERROR(IF(M91>0,ROUNDUP(Premissas!$B$12/M91,0),"sem lucro"),"") -> 175 | S91: Evitar (muitos gloss) | T91: N | V91: =IF(AND(T91="S",ISNUMBER(L91),ISNUMBER(F91)),L91*F91*X91,0) -> 0 | W91: =IF(AND(T91="S",ISNUMBER(Q91)),Q91*X91,0) -> 0 | X91: 1 | Y91: =IF(AND(T91="S",ISNUMBER(G91)),G91*X91,0) -> 0
A92: P91 | B92: Lápis Labial Multiuso (c/12) | C92: Pink 21 | D92: Maquiagem – Lábios | E92: 7 | F92: 12 | G92: 16.7 | H92: =IF(ISNUMBER(G92),IFERROR(G92/F92,""),"") -> 1.3916667 | I92: 3.96 | J92: 7.69 | K92: Confirmado | L92: 5.9 | M92: =IFERROR(L92*(1-Premissas!$B$5)*(1-Premissas!$B$6)-H92-Premissas!$B$7,"") -> 3.1572833 | N92: =IFERROR(M92/L92,"") -> 0.53513277 | O92: =IFERROR(L92*(1-Premissas!$B$8)-Premissas!$B$9-H92-Premissas!$B$7,"") -> -3.4496667 | P92: =IFERROR(L92*(1-Premissas!$B$10)-Premissas!$B$11-H92-Premissas!$B$7,"") -> -1.6716667 | Q92: =IFERROR(M92*F92,"") -> 37.8874 | R92: =IFERROR(IF(M92>0,ROUNDUP(Premissas!$B$12/M92,0),"sem lucro"),"") -> 317 | S92: Só em kit | T92: N | U92: Pacote com 12: R$ 1,39 cada | V92: =IF(AND(T92="S",ISNUMBER(L92),ISNUMBER(F92)),L92*F92*X92,0) -> 0 | W92: =IF(AND(T92="S",ISNUMBER(Q92)),Q92*X92,0) -> 0 | X92: 1 | Y92: =IF(AND(T92="S",ISNUMBER(G92)),G92*X92,0) -> 0
A93: P92 | B93: Blush Líquido Multifuncional | C93: Pink 21 | D93: Maquiagem – Rosto | E93: 7 | F93: 24 | G93: 93.99 | H93: =IF(ISNUMBER(G93),IFERROR(G93/F93,""),"") -> 3.91625 | I93: 19.9 | J93: 21.7 | K93: Estimado | L93: 15.9 | M93: =IFERROR(L93*(1-Premissas!$B$5)*(1-Premissas!$B$6)-H93-Premissas!$B$7,"") -> 10.0377 | N93: =IFERROR(M93/L93,"") -> 0.63130189 | O93: =IFERROR(L93*(1-Premissas!$B$8)-Premissas!$B$9-H93-Premissas!$B$7,"") -> 2.82575 | P93: =IFERROR(L93*(1-Premissas!$B$10)-Premissas!$B$11-H93-Premissas!$B$7,"") -> 3.80375 | Q93: =IFERROR(M93*F93,"") -> 240.9048 | R93: =IFERROR(IF(M93>0,ROUNDUP(Premissas!$B$12/M93,0),"sem lucro"),"") -> 100 | S93: Comprar | T93: S | U93: Mais barato que o The Pink (R$ 3,92 x R$ 6,62). Referência: blush líquido multiuso Pink 21 | V93: =IF(AND(T93="S",ISNUMBER(L93),ISNUMBER(F93)),L93*F93*X93,0) -> 381.6 | W93: =IF(AND(T93="S",ISNUMBER(Q93)),Q93*X93,0) -> 240.9048 | X93: 1 | Y93: =IF(AND(T93="S",ISNUMBER(G93)),G93*X93,0) -> 93.99
A94: P93 | B94: Body Splash Saarah 130ml | C94: Cap Life | D94: Perfumaria | E94: 7 | F94: 1 | G94: 6.99 | H94: =IF(ISNUMBER(G94),IFERROR(G94/F94,""),"") -> 6.99 | I94: 14.9 | J94: 19.9 | K94: Estimado | L94: 19.9 | M94: =IFERROR(L94*(1-Premissas!$B$5)*(1-Premissas!$B$6)-H94-Premissas!$B$7,"") -> 10.72595 | N94: =IFERROR(M94/L94,"") -> 0.53899246 | O94: =IFERROR(L94*(1-Premissas!$B$8)-Premissas!$B$9-H94-Premissas!$B$7,"") -> 3.272 | P94: =IFERROR(L94*(1-Premissas!$B$10)-Premissas!$B$11-H94-Premissas!$B$7,"") -> 3.93 | Q94: =IFERROR(M94*F94,"") -> 10.72595 | R94: =IFERROR(IF(M94>0,ROUNDUP(Premissas!$B$12/M94,0),"sem lucro"),"") -> 94 | S94: Opcional | T94: N | U94: Visto a R$ 6,40–6,99 em atacadistas; preço de varejo não achado | V94: =IF(AND(T94="S",ISNUMBER(L94),ISNUMBER(F94)),L94*F94*X94,0) -> 0 | W94: =IF(AND(T94="S",ISNUMBER(Q94)),Q94*X94,0) -> 0 | X94: 12 | Y94: =IF(AND(T94="S",ISNUMBER(G94)),G94*X94,0) -> 0
A95: P94 | B95: Corretivo Líquido Concealer (LR-4908) | C95: Love Rain | D95: Maquiagem – Rosto | E95: 7 | F95: 24 | G95: 160.4 | H95: =IF(ISNUMBER(G95),IFERROR(G95/F95,""),"") -> 6.6833333 | I95: 12.9 | J95: 12.9 | K95: Estimado | L95: 12.9 | M95: =IFERROR(L95*(1-Premissas!$B$5)*(1-Premissas!$B$6)-H95-Premissas!$B$7,"") -> 4.4491167 | N95: =IFERROR(M95/L95,"") -> 0.34489276 | O95: =IFERROR(L95*(1-Premissas!$B$8)-Premissas!$B$9-H95-Premissas!$B$7,"") -> -2.5813333 | P95: =IFERROR(L95*(1-Premissas!$B$10)-Premissas!$B$11-H95-Premissas!$B$7,"") -> -1.3633333 | Q95: =IFERROR(M95*F95,"") -> 106.7788 | R95: =IFERROR(IF(M95>0,ROUNDUP(Premissas!$B$12/M95,0),"sem lucro"),"") -> 225 | S95: Evitar (tem corretivo melhor) | T95: N | V95: =IF(AND(T95="S",ISNUMBER(L95),ISNUMBER(F95)),L95*F95*X95,0) -> 0 | W95: =IF(AND(T95="S",ISNUMBER(Q95)),Q95*X95,0) -> 0 | X95: 1 | Y95: =IF(AND(T95="S",ISNUMBER(G95)),G95*X95,0) -> 0
A96: P95 | B96: Batom Matte Cherry | C96: Vivai | D96: Maquiagem – Lábios | E96: 7 | F96: 24 | H96: =IF(ISNUMBER(G96),IFERROR(G96/F96,""),"") | K96: Estimado | M96: =IFERROR(L96*(1-Premissas!$B$5)*(1-Premissas!$B$6)-H96-Premissas!$B$7,"") | N96: =IFERROR(M96/L96,"") | O96: =IFERROR(L96*(1-Premissas!$B$8)-Premissas!$B$9-H96-Premissas!$B$7,"") | P96: =IFERROR(L96*(1-Premissas!$B$10)-Premissas!$B$11-H96-Premissas!$B$7,"") | Q96: =IFERROR(M96*F96,"") | R96: =IFERROR(IF(M96>0,ROUNDUP(Premissas!$B$12/M96,0),"sem lucro"),"") | S96: Confirmar preço | T96: N | U96: Preço escondido no print | V96: =IF(AND(T96="S",ISNUMBER(L96),ISNUMBER(F96)),L96*F96*X96,0) -> 0 | W96: =IF(AND(T96="S",ISNUMBER(Q96)),Q96*X96,0) -> 0 | X96: 1 | Y96: =IF(AND(T96="S",ISNUMBER(G96)),G96*X96,0) -> 0
A97: P96 | B97: Batom Cintilante Viv | C97: Vivai | D97: Maquiagem – Lábios | E97: 7 | F97: 24 | H97: =IF(ISNUMBER(G97),IFERROR(G97/F97,""),"") | K97: Estimado | M97: =IFERROR(L97*(1-Premissas!$B$5)*(1-Premissas!$B$6)-H97-Premissas!$B$7,"") | N97: =IFERROR(M97/L97,"") | O97: =IFERROR(L97*(1-Premissas!$B$8)-Premissas!$B$9-H97-Premissas!$B$7,"") | P97: =IFERROR(L97*(1-Premissas!$B$10)-Premissas!$B$11-H97-Premissas!$B$7,"") | Q97: =IFERROR(M97*F97,"") | R97: =IFERROR(IF(M97>0,ROUNDUP(Premissas!$B$12/M97,0),"sem lucro"),"") | S97: Confirmar preço | T97: N | U97: Preço escondido no print | V97: =IF(AND(T97="S",ISNUMBER(L97),ISNUMBER(F97)),L97*F97*X97,0) -> 0 | W97: =IF(AND(T97="S",ISNUMBER(Q97)),Q97*X97,0) -> 0 | X97: 1 | Y97: =IF(AND(T97="S",ISNUMBER(G97)),G97*X97,0) -> 0
A98: P97 | B98: Pó Solto Banana (B101) | C98: Belle Angel | D98: Maquiagem – Rosto | E98: 8 | F98: 19 | G98: 119.9 | H98: =IF(ISNUMBER(G98),IFERROR(G98/F98,""),"") -> 6.3105263 | I98: 12.9 | J98: 14.9 | K98: Estimado | L98: 13.9 | M98: =IFERROR(L98*(1-Premissas!$B$5)*(1-Premissas!$B$6)-H98-Premissas!$B$7,"") -> 5.7624237 | N98: =IFERROR(M98/L98,"") -> 0.41456285 | O98: =IFERROR(L98*(1-Premissas!$B$8)-Premissas!$B$9-H98-Premissas!$B$7,"") -> -1.3285263 | P98: =IFERROR(L98*(1-Premissas!$B$10)-Premissas!$B$11-H98-Premissas!$B$7,"") -> -0.19052632 | Q98: =IFERROR(M98*F98,"") -> 109.48605 | R98: =IFERROR(IF(M98>0,ROUNDUP(Premissas!$B$12/M98,0),"sem lucro"),"") -> 174 | S98: Opcional | T98: N | U98: Caixa com 19. O Pó de Tapioca Miss Rôse é mais barato | V98: =IF(AND(T98="S",ISNUMBER(L98),ISNUMBER(F98)),L98*F98*X98,0) -> 0 | W98: =IF(AND(T98="S",ISNUMBER(Q98)),Q98*X98,0) -> 0 | X98: 1 | Y98: =IF(AND(T98="S",ISNUMBER(G98)),G98*X98,0) -> 0
A99: P98 | B99: Blush (ME003) | C99: Belle Angel | D99: Maquiagem – Rosto | E99: 8 | F99: 24 | G99: 142.2 | H99: =IF(ISNUMBER(G99),IFERROR(G99/F99,""),"") -> 5.925 | I99: 12.9 | J99: 12.9 | K99: Estimado | L99: 12.9 | M99: =IFERROR(L99*(1-Premissas!$B$5)*(1-Premissas!$B$6)-H99-Premissas!$B$7,"") -> 5.20745 | N99: =IFERROR(M99/L99,"") -> 0.40367829 | O99: =IFERROR(L99*(1-Premissas!$B$8)-Premissas!$B$9-H99-Premissas!$B$7,"") -> -1.823 | P99: =IFERROR(L99*(1-Premissas!$B$10)-Premissas!$B$11-H99-Premissas!$B$7,"") -> -0.605 | Q99: =IFERROR(M99*F99,"") -> 124.9788 | R99: =IFERROR(IF(M99>0,ROUNDUP(Premissas!$B$12/M99,0),"sem lucro"),"") -> 193 | S99: Opcional | T99: N | V99: =IF(AND(T99="S",ISNUMBER(L99),ISNUMBER(F99)),L99*F99*X99,0) -> 0 | W99: =IF(AND(T99="S",ISNUMBER(Q99)),Q99*X99,0) -> 0 | X99: 1 | Y99: =IF(AND(T99="S",ISNUMBER(G99)),G99*X99,0) -> 0
A100: P99 | B100: Lip Cream You Me com Chaveiro | C100: Belle Angel | D100: Maquiagem – Lábios | E100: 8 | F100: 24 | G100: 129.3 | H100: =IF(ISNUMBER(G100),IFERROR(G100/F100,""),"") -> 5.3875 | I100: 12.9 | J100: 12.9 | K100: Estimado | L100: 12.9 | M100: =IFERROR(L100*(1-Premissas!$B$5)*(1-Premissas!$B$6)-H100-Premissas!$B$7,"") -> 5.74495 | N100: =IFERROR(M100/L100,"") -> 0.44534496 | O100: =IFERROR(L100*(1-Premissas!$B$8)-Premissas!$B$9-H100-Premissas!$B$7,"") -> -1.2855 | P100: =IFERROR(L100*(1-Premissas!$B$10)-Premissas!$B$11-H100-Premissas!$B$7,"") -> -0.0675 | Q100: =IFERROR(M100*F100,"") -> 137.8788 | R100: =IFERROR(IF(M100>0,ROUNDUP(Premissas!$B$12/M100,0),"sem lucro"),"") -> 175 | S100: Evitar (muitos gloss) | T100: N | V100: =IF(AND(T100="S",ISNUMBER(L100),ISNUMBER(F100)),L100*F100*X100,0) -> 0 | W100: =IF(AND(T100="S",ISNUMBER(Q100)),Q100*X100,0) -> 0 | X100: 1 | Y100: =IF(AND(T100="S",ISNUMBER(G100)),G100*X100,0) -> 0
...

Sheet Kits
A1: Kit | B1: Item 1 | C1: Item 2 | D1: Item 3 | E1: Item 4 | F1: Item 5 | G1: Custo do kit | H1: Preço de venda | I1: Lucro seu site | J1: Lucro Mercado Livre | K1: Lucro Shopee | L1: Kits/mês p/ meta (seu site)
A2: Pele de Vidro | B2: P23 | C2: P25 | D2: P24 | G2: =IFERROR(INDEX(Produtos!$H$2:$H$110,MATCH(B2,Produtos!$A$2:$A$110,0)),0)+IFERROR(INDEX(Produtos!$H$2:$H$110,MATCH(C2,Produtos!$A$2:$A$110,0)),0)+IFERROR(INDEX(Produtos!$H$2:$H$110,MATCH(D2,Produtos!$A$2:$A$110,0)),0)+IFERROR(INDEX(Produtos!$H$2:$H$110,MATCH(E2,Produtos!$A$2:$A$110,0)),0)+IFERROR(INDEX(Produtos!$H$2:$H$110,MATCH(F2,Produtos!$A$2:$A$110,0)),0) -> 18.9 | H2: 49.9 | I2: =H2*(1-Premissas!$B$5)*(1-Premissas!$B$6)-G2-Premissas!$B$7 -> 27.03095 | J2: =H2*(1-Premissas!$B$8)-Premissas!$B$9-G2-Premissas!$B$7 -> 17.762 | K2: =H2*(1-Premissas!$B$10)-Premissas!$B$11-G2-Premissas!$B$7 -> 16.02 | L2: =IF(I2>0,ROUNDUP(Premissas!$B$12/I2,0),"sem lucro") -> 37
A3: Pele Perfeita | B3: P02 | C3: P06 | D3: P07 | E3: P36 | G3: =IFERROR(INDEX(Produtos!$H$2:$H$110,MATCH(B3,Produtos!$A$2:$A$110,0)),0)+IFERROR(INDEX(Produtos!$H$2:$H$110,MATCH(C3,Produtos!$A$2:$A$110,0)),0)+IFERROR(INDEX(Produtos!$H$2:$H$110,MATCH(D3,Produtos!$A$2:$A$110,0)),0)+IFERROR(INDEX(Produtos!$H$2:$H$110,MATCH(E3,Produtos!$A$2:$A$110,0)),0)+IFERROR(INDEX(Produtos!$H$2:$H$110,MATCH(F3,Produtos!$A$2:$A$110,0)),0) -> 23.595833 | H3: 49.9 | I3: =H3*(1-Premissas!$B$5)*(1-Premissas!$B$6)-G3-Premissas!$B$7 -> 22.335117 | J3: =H3*(1-Premissas!$B$8)-Premissas!$B$9-G3-Premissas!$B$7 -> 13.066167 | K3: =H3*(1-Premissas!$B$10)-Premissas!$B$11-G3-Premissas!$B$7 -> 11.324167 | L3: =IF(I3>0,ROUNDUP(Premissas!$B$12/I3,0),"sem lucro") -> 45
A4: Rotina Skincare | B4: P09 | C4: P10 | D4: P12 | G4: =IFERROR(INDEX(Produtos!$H$2:$H$110,MATCH(B4,Produtos!$A$2:$A$110,0)),0)+IFERROR(INDEX(Produtos!$H$2:$H$110,MATCH(C4,Produtos!$A$2:$A$110,0)),0)+IFERROR(INDEX(Produtos!$H$2:$H$110,MATCH(D4,Produtos!$A$2:$A$110,0)),0)+IFERROR(INDEX(Produtos!$H$2:$H$110,MATCH(E4,Produtos!$A$2:$A$110,0)),0)+IFERROR(INDEX(Produtos!$H$2:$H$110,MATCH(F4,Produtos!$A$2:$A$110,0)),0) -> 17.1 | H4: 39.9 | I4: =H4*(1-Premissas!$B$5)*(1-Premissas!$B$6)-G4-Premissas!$B$7 -> 19.42595 | J4: =H4*(1-Premissas!$B$8)-Premissas!$B$9-G4-Premissas!$B$7 -> 10.762 | K4: =H4*(1-Premissas!$B$10)-Premissas!$B$11-G4-Premissas!$B$7 -> 9.82 | L4: =IF(I4>0,ROUNDUP(Premissas!$B$12/I4,0),"sem lucro") -> 52
A5: Olhar Poderoso | B5: P22 | C5: P22 | D5: P22 | E5: P105 | F5: P31 | G5: =IFERROR(INDEX(Produtos!$H$2:$H$110,MATCH(B5,Produtos!$A$2:$A$110,0)),0)+IFERROR(INDEX(Produtos!$H$2:$H$110,MATCH(C5,Produtos!$A$2:$A$110,0)),0)+IFERROR(INDEX(Produtos!$H$2:$H$110,MATCH(D5,Produtos!$A$2:$A$110,0)),0)+IFERROR(INDEX(Produtos!$H$2:$H$110,MATCH(E5,Produtos!$A$2:$A$110,0)),0)+IFERROR(INDEX(Produtos!$H$2:$H$110,MATCH(F5,Produtos!$A$2:$A$110,0)),0) -> 21.110833 | H5: 44.9 | I5: =H5*(1-Premissas!$B$5)*(1-Premissas!$B$6)-G5-Premissas!$B$7 -> 20.117617 | J5: =H5*(1-Premissas!$B$8)-Premissas!$B$9-G5-Premissas!$B$7 -> 11.151167 | K5: =H5*(1-Premissas!$B$10)-Premissas!$B$11-G5-Premissas!$B$7 -> 9.8091667 | L5: =IF(I5>0,ROUNDUP(Premissas!$B$12/I5,0),"sem lucro") -> 50
A6: Sobrancelha Perfeita | B6: P37 | C6: P38 | D6: P31 | G6: =IFERROR(INDEX(Produtos!$H$2:$H$110,MATCH(B6,Produtos!$A$2:$A$110,0)),0)+IFERROR(INDEX(Produtos!$H$2:$H$110,MATCH(C6,Produtos!$A$2:$A$110,0)),0)+IFERROR(INDEX(Produtos!$H$2:$H$110,MATCH(D6,Produtos!$A$2:$A$110,0)),0)+IFERROR(INDEX(Produtos!$H$2:$H$110,MATCH(E6,Produtos!$A$2:$A$110,0)),0)+IFERROR(INDEX(Produtos!$H$2:$H$110,MATCH(F6,Produtos!$A$2:$A$110,0)),0) -> 16.65 | H6: 34.9 | I6: =H6*(1-Premissas!$B$5)*(1-Premissas!$B$6)-G6-Premissas!$B$7 -> 15.17345 | J6: =H6*(1-Premissas!$B$8)-Premissas!$B$9-G6-Premissas!$B$7 -> 6.812 | K6: =H6*(1-Premissas!$B$10)-Premissas!$B$11-G6-Premissas!$B$7 -> 6.27 | L6: =IF(I6>0,ROUNDUP(Premissas!$B$12/I6,0),"sem lucro") -> 66
A7: Lábios Suculentos | B7: P28 | C7: P29 | D7: P27 | G7: =IFERROR(INDEX(Produtos!$H$2:$H$110,MATCH(B7,Produtos!$A$2:$A$110,0)),0)+IFERROR(INDEX(Produtos!$H$2:$H$110,MATCH(C7,Produtos!$A$2:$A$110,0)),0)+IFERROR(INDEX(Produtos!$H$2:$H$110,MATCH(D7,Produtos!$A$2:$A$110,0)),0)+IFERROR(INDEX(Produtos!$H$2:$H$110,MATCH(E7,Produtos!$A$2:$A$110,0)),0)+IFERROR(INDEX(Produtos!$H$2:$H$110,MATCH(F7,Produtos!$A$2:$A$110,0)),0) -> 17.016667 | H7: 34.9 | I7: =H7*(1-Premissas!$B$5)*(1-Premissas!$B$6)-G7-Premissas!$B$7 -> 14.806783 | J7: =H7*(1-Premissas!$B$8)-Premissas!$B$9-G7-Premissas!$B$7 -> 6.4453333 | K7: =H7*(1-Premissas!$B$10)-Premissas!$B$11-G7-Premissas!$B$7 -> 5.9033333 | L7: =IF(I7>0,ROUNDUP(Premissas!$B$12/I7,0),"sem lucro") -> 68
A8: Perfumada (splash + creme) | B8: P52 | C8: P54 | G8: =IFERROR(INDEX(Produtos!$H$2:$H$110,MATCH(B8,Produtos!$A$2:$A$110,0)),0)+IFERROR(INDEX(Produtos!$H$2:$H$110,MATCH(C8,Produtos!$A$2:$A$110,0)),0)+IFERROR(INDEX(Produtos!$H$2:$H$110,MATCH(D8,Produtos!$A$2:$A$110,0)),0)+IFERROR(INDEX(Produtos!$H$2:$H$110,MATCH(E8,Produtos!$A$2:$A$110,0)),0)+IFERROR(INDEX(Produtos!$H$2:$H$110,MATCH(F8,Produtos!$A$2:$A$110,0)),0) -> 13.4 | H8: 44.9 | I8: =H8*(1-Premissas!$B$5)*(1-Premissas!$B$6)-G8-Premissas!$B$7 -> 27.82845 | J8: =H8*(1-Premissas!$B$8)-Premissas!$B$9-G8-Premissas!$B$7 -> 18.862 | K8: =H8*(1-Premissas!$B$10)-Premissas!$B$11-G8-Premissas!$B$7 -> 17.52 | L8: =IF(I8>0,ROUNDUP(Premissas!$B$12/I8,0),"sem lucro") -> 36
A9: Presente Masculino (2 splash) | B9: P53 | C9: P53 | G9: =IFERROR(INDEX(Produtos!$H$2:$H$110,MATCH(B9,Produtos!$A$2:$A$110,0)),0)+IFERROR(INDEX(Produtos!$H$2:$H$110,MATCH(C9,Produtos!$A$2:$A$110,0)),0)+IFERROR(INDEX(Produtos!$H$2:$H$110,MATCH(D9,Produtos!$A$2:$A$110,0)),0)+IFERROR(INDEX(Produtos!$H$2:$H$110,MATCH(E9,Produtos!$A$2:$A$110,0)),0)+IFERROR(INDEX(Produtos!$H$2:$H$110,MATCH(F9,Produtos!$A$2:$A$110,0)),0) -> 13.6 | H9: 44.9 | I9: =H9*(1-Premissas!$B$5)*(1-Premissas!$B$6)-G9-Premissas!$B$7 -> 27.62845 | J9: =H9*(1-Premissas!$B$8)-Premissas!$B$9-G9-Premissas!$B$7 -> 18.662 | K9: =H9*(1-Premissas!$B$10)-Premissas!$B$11-G9-Premissas!$B$7 -> 17.32 | L9: =IF(I9>0,ROUNDUP(Premissas!$B$12/I9,0),"sem lucro") -> 37
A10: Make Completa | B10: P72 | C10: P69 | D10: P66 | E10: P58 | G10: =IFERROR(INDEX(Produtos!$H$2:$H$110,MATCH(B10,Produtos!$A$2:$A$110,0)),0)+IFERROR(INDEX(Produtos!$H$2:$H$110,MATCH(C10,Produtos!$A$2:$A$110,0)),0)+IFERROR(INDEX(Produtos!$H$2:$H$110,MATCH(D10,Produtos!$A$2:$A$110,0)),0)+IFERROR(INDEX(Produtos!$H$2:$H$110,MATCH(E10,Produtos!$A$2:$A$110,0)),0)+IFERROR(INDEX(Produtos!$H$2:$H$110,MATCH(F10,Produtos!$A$2:$A$110,0)),0) -> 22.533125 | H10: 59.9 | I10: =H10*(1-Premissas!$B$5)*(1-Premissas!$B$6)-G10-Premissas!$B$7 -> 32.802825 | J10: =H10*(1-Premissas!$B$8)-Premissas!$B$9-G10-Premissas!$B$7 -> 22.928875 | K10: =H10*(1-Premissas!$B$10)-Premissas!$B$11-G10-Premissas!$B$7 -> 20.386875 | L10: =IF(I10>0,ROUNDUP(Premissas!$B$12/I10,0),"sem lucro") -> 31
A11: Pele Pink 21 | B11: P89 | C11: P66 | D11: P92 | E11: P58 | G11: =IFERROR(INDEX(Produtos!$H$2:$H$110,MATCH(B11,Produtos!$A$2:$A$110,0)),0)+IFERROR(INDEX(Produtos!$H$2:$H$110,MATCH(C11,Produtos!$A$2:$A$110,0)),0)+IFERROR(INDEX(Produtos!$H$2:$H$110,MATCH(D11,Produtos!$A$2:$A$110,0)),0)+IFERROR(INDEX(Produtos!$H$2:$H$110,MATCH(E11,Produtos!$A$2:$A$110,0)),0)+IFERROR(INDEX(Produtos!$H$2:$H$110,MATCH(F11,Produtos!$A$2:$A$110,0)),0) -> 15.463958 | H11: 49.9 | I11: =H11*(1-Premissas!$B$5)*(1-Premissas!$B$6)-G11-Premissas!$B$7 -> 30.466992 | J11: =H11*(1-Premissas!$B$8)-Premissas!$B$9-G11-Premissas!$B$7 -> 21.198042 | K11: =H11*(1-Premissas!$B$10)-Premissas!$B$11-G11-Premissas!$B$7 -> 19.456042 | L11: =IF(I11>0,ROUNDUP(Premissas!$B$12/I11,0),"sem lucro") -> 33
A13: Os itens são IDs da aba Produtos (passe o mouse para ver o nome). Repetir um ID = mais de uma unidade no kit.
